Workbook

Sheet Instruções de uso
B1: @dropdown
D2: Carteira "Nasser" Family Investimentos
A7: Planilha de Rentabilidade
A10: Orientações e Sugestões de Utilização
A12: Preencha a planilha com os dados do investimento. Coloque suas próprias informações para adaptar a planilha à sua vida;
A14: ATENÇÃO: não altere as células da cor CINZA;
A16: Busque as informações em suas corretoras e/ou bancos.
A18: A planilha serve como BASE para calcular o retorno de suas aplicações financeiras. Você pode fazer modificações se desejar.
A20: IMPORTANTE: leia as instruções de uso da planilha.

Sheet NCs

Sheet BenchMarK
A2: MES A MES
A3: DATA | B3: 01/21 | C3: 02/21 | D3: 03/21 | E3: 04/21 | F3: 05/21 | G3: 06/21 | H3: 07/21 | I3: 08/21 | J3: 44440 | K3: 10/21
A5: BENCHMARK IBOV | B5: -3.32 | C5: -0.0437 | D5: 0.06 | E5: 0.0194 | F5: 0.061583 | G5: 0.0046 | H5: -0.039438 | I5: -0.0247 | J5: -6.57
A7: CARTEIRA NASSER FAMILY | B7: 0 | C7: 0 | D7: ='Planilha de Rentabilidade'!AO67 -> -1 | E7: ='Planilha de Rentabilidade'!AP67 | F7: =+'Planilha de Rentabilidade'!AQ67 | G7: 0 | J7: ='Planilha de Rentabilidade'!AU67 | K7: ='Planilha de Rentabilidade'!AV67
A11: BenchMarket Acumulado | G11: C.N.F. mensal
B12: IBOV | C12: C.N.M. | E12: CDI - DI
A13: 01/24 | B13: 0.1256 | C13: 0 | E13: 0.0116 | G13: ='Planilha de Rentabilidade'!AI7 -> 0.0082489277
A14: 02/24 | B14: 0.0395 | C14: 0 | E14: 0.0066 | G14: ='Planilha de Rentabilidade'!AI15 -> -0.0089058383
A15: 03/24 | B15: 0 | C15: 0 | E15: 0 | G15: 0
A16: 04/24 | B16: 0 | C16: 0 | E16: 0 | G16: 0
A17: 05/24 | B17: 0 | C17: 0 | E17: 0 | G17: 0
A18: 06/24 | B18: 0 | C18: 0 | E18: 0 | G18: 0
A19: 07/24 | B19: 0 | C19: 0 | E19: 0 | G19: 0
A20: 08/24 | B20: 0 | C20: 0 | E20: 0 | G20: 0
A21: 09/24 | B21: 0 | C21: 0 | E21: 0 | G21: 0
A22: 10/24 | B22: 0 | C22: 0 | E22: 0 | G22: 0
A23: 11/24 | B23: 0 | E23: 0 | G23: 0
A24: 12/24 | B24: 0 | E24: 0 | G24: 0

Sheet % de Alocação da Carteira 01_25
B2: ANALISE % de Alocação da Carteira "Nasser Family"p/ Produto Financeiro (01/2024) | M2: ALOCAÇÃO % COMPACTA
E3: =+SUM(E4:E14) -> 1
B4: CAIXA | D4: =+'Planilha de Rentabilidade'!E6 -> -333138 | E4: =D4/$E$15 -> -0.10559144 | L4: IPCA + | M4: =SUM(D5:D7) -> 416980.73 | N4: =M4/$M$15 -> 0.13216624
B5: TESOURO IPCA+2035 | D5: =+'Planilha de Rentabilidade'!Q6 -> 63463 | E5: =D5/$E$15 -> 0.020115236 | M5: 0 | N5: =M5/$M$15 -> 0
B6: DEBENTURE | D6: =+'Planilha de Rentabilidade'!P6 -> 231658.11 | E6: =D6/$E$15 -> 0.073426368 | M6: 0 | N6: =M6/$M$15 -> 0
B7: CRI CRA | D7: ='Planilha de Rentabilidade'!O6 -> 121859.62 | E7: =D7/$E$15 -> 0.038624632 | L7: LCA | M7: =+D11 -> 0 | N7: =M7/$M$15 -> 0
B8: TESOURO SELIC + LFTS11 | D8: ='Planilha de Rentabilidade'!C6+'Planilha de Rentabilidade'!D6+'Planilha de Rentabilidade'!S6+'Planilha de Rentabilidade'!F6 -> 186765.12 | E8: =D8/$E$15 -> 0.059197083 | L8: RENDA FIXA | M8: =D8+D12+D13 -> 973746.18 | N8: =M8/$M$15 -> 0.30863865
B9: MOEDAS | D9: ='Planilha de Rentabilidade'!L6 -> 89125.92 | E9: =D9/$E$15 -> 0.028249357 | L9: GOLD+$$ | M9: =+D10 -> 339349 | N9: =M9/$M$15 -> 0.10756008
B10: GOLD+$ | D10: ='Planilha de Rentabilidade'!M6 -> 339349 | E10: =D10/$E$15 -> 0.10756008 | L10: MOEDAS | M10: =D9 -> 89125.92 | N10: =M10/$M$15 -> 0.028249357
B11: LCA | D11: =0 -> 0 | E11: =D11/$E$15 -> 0 | N11: =M11/$M$15 -> 0
B12: FUNDO DI | D12: ='Planilha de Rentabilidade'!G6+'Planilha de Rentabilidade'!I6+'Planilha de Rentabilidade'!J6 -> 541210.38 | E12: =D12/$E$15 -> 0.17154207 | L12: CAIXA | M12: =+D4 -> -333138 | N12: =M12/$M$15 -> -0.10559144
B13: CDB DI | D13: ='Planilha de Rentabilidade'!H6+'Planilha de Rentabilidade'!K6 -> 245770.68 | E13: =D13/$E$15 -> 0.077899489 | N13: =M13/$M$15 -> 0
B14: RENDA VARIAVEL | D14: =B33 -> 1668907.8 | E14: =D14/$E$15 -> 0.52897712 | L14: Renda Variavel | M14: =D14 -> 1668907.8 | N14: =M14/$M$15 -> 0.52897712
C15: Total da Carteira Nasser Family ==> | E15: =SUM(D4:D14) -> 3154971.6 | M15: =SUM(M4:M14) -> 3154971.6 | N15: =SUM(N4:N14) -> 1
B18: ANALISE % Alocação da Carteira "Nasser Family" RENDA VARIAVEL(01/2024)
C19: % Renda Variavel Alocadas por Setor
B20: =+'Planilha de Rentabilidade'!Z6+'Planilha de Rentabilidade'!W6 -> 0 | C20: =B20/$B$33 -> 0 | D20: IRON ORE
B21: 0 | C21: =B21/$B$33 -> 0 | D21: SOJA
B22: =+'Planilha de Rentabilidade'!AF6+'Planilha de Rentabilidade'!U6 -> 996194.32 | C22: =B22/$B$33 -> 0.59691393 | D22: Electric Vehicle
B23: =+'Planilha de Rentabilidade'!V6+'Planilha de Rentabilidade'!AD6 -> 151536 | C23: =B23/$B$33 -> 0.090799503 | D23: MELI
B24: =+'Planilha de Rentabilidade'!AE6 -> 0 | C24: =B24/$B$33 -> 0 | D24: LITHIUM
B25: 0 | C25: =B25/$B$33 -> 0 | D25: ENERGIA
B26: =0 -> 0 | C26: =B26/$B$33 -> 0 | D26: CELULOSE
B27: =+'Planilha de Rentabilidade'!AA6 -> 0 | C27: =B27/$B$33 -> 0 | D27: Saude
B28: =+'Planilha de Rentabilidade'!R6 -> 176421 | C28: =B28/$B$33 -> 0.10571045 | D28: AURA
B29: =+'Planilha de Rentabilidade'!X6+'Planilha de Rentabilidade'!AC6 -> 174080.5 | C29: =B29/$B$33 -> 0.10430804 | D29: AMD
B30: ='Planilha de Rentabilidade'!T6+'Planilha de Rentabilidade'!AG6 -> 0 | C30: =B30/$B$33 -> 0 | D30: APPLE
B31: ='Planilha de Rentabilidade'!N6+'Planilha de Rentabilidade'!AH6 -> 0 | C31: =B31/$B$33 -> 0 | D31: INTEL
B32: =+'Planilha de Rentabilidade'!AB6 -> 170676 | C32: =B32/$B$33 -> 0.10226808 | D32: WEGE
B33: =SUM(B20:B32) -> 1668907.8 | C33: =B33/$B$33 -> 1

Sheet Planilha de Rentabilidade
A1: Mês | B1: Descrição | C1: Tesouro Alexa | D1: Tesouro Nasser | E1: SALDOS | F1: LFTS11 BTG ALEXA | G1: FUNDO BTG DIGITAL SELIC FIRF | H1: CDB NU NASSER | I1: BB FUNDO-RF LP HIGH | J1: FUNDO BTG CDB PLUS FIRF CRPR | K1: CDB - SANTANDER | L1: MOEDAS - WISE | M1: GOLD + CASH | N1: INTEL NASSER - ITLC34 | O1: CRI OPEA IPCA+6,63%2040 BTG | P1: DEBENTURE IGUA RIO IRJS15 IPCA+7,60% | Q1: TESOURO ALEXA IPCA+ 2029 | R1: AURA33 NASSER BTG | S1: LFT-S11 BTG NASSER | T1: AAPL34 BTG NASSER | U1: TSLA34 - BTG NASSER | V1: MELI34 BTG NASSER | W1: CMIN3 NASSER BTG | X1: A1MD34 AMD BTG ALEXA | Y1: ASML34 BTG NASSER | Z1: VALE3 NASSER BTG | AA1: HAPV3 HAPVIDA BTG ALEXA | AB1: WEGE3 - BTG NASSER | AC1: AMD A1MD34 BTG NASSER | AD1: MELI34 BTG ALEXA | AE1: SIGMA BTG ALEXA | AF1: TESLA ALEXA BTG | AG1: AAPL34 ALEXA BTG | AH1: ITLC34 ALEXA BTG | AI1: Patrimônio | AL1: @
A2: 45658 | B2: Valor em 31/12/2024 | C2: =+(12508.62+20736.77)*0+(12535.93+20782.67)*0+(12556.6+20817.08)*0+(12598.75+20886.49)*0+(12620+20921)*0+(12641.27+20955.72)*0+(12648.27+20967.15) -> 33615.42 | D2: =+149296.91*0+149622.35*0+149874.58*0+150042.05*0+150211.96*0+150383.65*0+150641.47*0+150891.01*0+150973.61 -> 150973.61 | E2: =+(+157896.94+105619.23)*0+(120284.75-11217.78+110000)*0+(-1007-21656+110152)*0+(-4041.8-24669+106500+114581+33638)*0+(-44568.88+115309-40000)*0+(-63001-40260+112378)*0+(-59384-42365+112378)*0+(+21258.2+1620)*0+(+43575-6839)*0+(-57105-14912+9135+36122)*0+((-5942.97-57120)+(+36122))*0+(-66864-443+20000+12736)*0+((-73278-36511)+(-38726-28000))*0+((-39639-28000-36468)+(-14720-13392))*0+((-39639-28000-36468-59711+12751)+(-13392+3746+80545+41069))*0+((-39639-28000-36468-59711+12751)+(121057-9655))*0+((+300-28000+531-68711+12751)+(+11656+3322+62397+258))*0+((+300-28000+531+875-68711+12766)+(+80895.41+3529))*0+(-43253.36+120881-512)*0+((+77627+25980+5593+6472-4170)+(-55911+531+12766+466))*0+((+77627+25980-4170+5593)+(+985+12766+408+531+475-55911))*0+((+103386.01+1406+6472)+(-71761+985+17191+408+531+475))*0+((+9897+60942+6444)+(+231+17191+855+475))*0+((+70826+6444)+(+231+855+475))*0+((-11781+6444)+(+231+855+475))*0+((-14446+6444)+(+231+475+355))*0+((-55637-46658)+(700+231+355+475)) -> -100534 | F2: =+(+350+50)*145.4 -> 58160 | G2: =+113120.91*0+113364.9*0+113560.98*0+113620.29*0+113810.75*0+113873.59*0+114070.01*0+114317.49*0+114378.69 -> 114378.69 | H2: =+17191*0+17201.19*0+17211.08 -> 17211.08 | I2: =+185984.49*0+186360.05*0+186683.67*0+187308.72*0+187415*0+187520.82*0+187721.71*0+187830.99*0+187931.6*0+188042.95 -> 188042.95 | J2: =+229637.76*0+230273.34*0+230656.49*0+230783.54*0+231164.99*0+231291.84*0+231674.36*0+232190.08*0+232331.89 -> 232331.89 | K2: =+224902*0+225149.4*0+225521.99*0+225770.72*0+226893.42*0+227519.55 -> 227519.55 | L2: =+122965.86*0+146740.18*0+148753*0+130221*0+(129920-18962.43)*0+111978*0+(112056.62-14410)*0+95950*0+96233*0+98142*0+97927*0+98118*0+98337*0+86133*0+86140.21*0+(72134.11*0+72063.5+2000-13366.37)*0+60723.67*0+61075*0+60621.02*0+60020.65*0+59982.56 -> 59982.56 | M2: =+(+163088.45+23393.68+12308.53+18823.14+18962.43)*0+(252047.43+13833.97+13366.37)*0+284245.72 -> 284245.72 | N2: 0 | O2: =+120000*0+120114.45*0+120177.45*0+120242.46*0+120323.39*0+120433.9*0+120655.21*0+120755.05*0+120825.34*0+120875.65 -> 120875.65 | P2: =+227708.9*0+228061.55*0+228240*0+228459.98*0+228547.9*0+228768.26*0+229102.07*0+229358.02*0+229561.48*0+229663.28 -> 229663.28 | Q2: =+62076.13*0+62422.89*0+62000.18*0+61926.54*0+62123.52*0+62516.1*0+62619.35 -> 62619.35 | R2: =+(+2250+600)*91.03 -> 259435.5 | S2: =+(+404+5+45-200)*145.4 -> 36931.6 | T2: 0 | U2: =+(+10345-500)*77.52 -> 763184.4 | V2: =+1700*92.22 -> 156774 | W2: 0 | X2: =+(+270+140)*147 -> 60270 | Y2: 0 | Z2: =+(+2700-500-500+2100-600-500-500-700-500)*71.96 -> 71960 | AA2: =+(+900+800+600+300+100+700)*14.73 -> 50082 | AB2: =+(+3100+100+1000)*48.51 -> 203742 | AC2: =+(+700+110+200)*147 -> 148470 | AD2: =+450*92.22 -> 41499 | AE2: 0 | AF2: =+(+1300+660)*77.52 -> 151939.2 | AG2: 0 | AH2: 0 | AI2: =SUM(C2:AH2) -> 3623373.5
B3: Investimento (+) | C3: 0 | D3: 0 | E3: 0 | F3: =+50*145.35+37*145.27+13*145.6 -> 14535.29 | G3: 0 | H3: 0 | I3: 0 | J3: 0 | K3: 0 | L3: =+4000+6500+6500+8000+10000+4500+17000+10000+5000+10000+5000+6000 -> 92500 | M3: =+24568+15566+14970 -> 55104 | O3: 0 | P3: 0 | Q3: 0 | R3: 0 | S3: 0 | T3: 0 | U3: =+300*73.01 + 300*72.21 + 200*72.01 +300*71.76 +99*71.11 + 100*70.74 + 100*71.02 + 99*70.16 + 99*70.36 + 30*71.09 + 36*71.21 + 30*70.91 + 10*71.29 + 10*71.23 + 100*70.16 + 50*70.53 -> 133414.63 | V3: =+100*93.15 -> 9315 | W3: 0 | X3: 0 | Y3: 0 | Z3: 0 | AA3: =+500*13.43 + 100*13.5 + 100*13.5 + 100*13.5 + 100*13.51 + 100*13.4 + 100*13.42+1000*13.37 -> 28168 | AB3: 0 | AC3: 0 | AD3: 0 | AE3: 0 | AF3: =+20*71.39 + 20*71.09 + 20*71.18 + 20*71.02 + 20*70.91 + 20*71.14 + 10*71.23 + 10*71.3 + 10*71.05 + 80*70.73 -> 16328.8 | AG3: 0 | AH3: 0 | AI3: =SUM(C3:AH3) -> 349365.72 | AW3: 44227 | AX3: 44255
B4: Resgate (-) | C4: 0 | D4: 0 | E4: =+E6-E2 -> -232604 | F4: =-100*145.75 - 100*145.75 - 100*145.75 - 100*145.74 - 100*145.75 -> -72874 | G4: 0 | H4: =-950-100-200-400-200 -> -1850 | I4: 0 | J4: 0 | K4: 0 | L4: =-3158-24568-15566-14970 -> -58262 | M4: 0 | N4: 0 | O4: 0 | P4: 0 | Q4: 0 | R4: =-100*96.7 - 100*95.88 - 100*95.5 - 17*95.72 - 83*95.81 - 100*96.7 -100*93.27 - 100*93.28 -50*104.53 - 50*104.59 - 50*108.01 - 50*108.1-100*114.36-100*114.49-30*114.99-30*115.22-30*115.42 -30*124.81 - 30*124.88 -50*115.44 -> -134490.57 | S4: =+(-200*145.75 -16*145.82 - 38*145.83) -> -37024.66 | T4: 0 | U4: 0 | V4: =-100*94.12 - 50*94.1 -15*93.93 - 85*93.93 - 1*94.28 - 15*94.28 - 84*94.28 - 100*94.43 - 100*94.51 - 8*94.65 - 30*94.65 - 62*94.65 -> -61297 | W4: 0 | X4: =0 -> 0 | Y4: 0 | Z4: =-100*75.88 - 100*75.86 - 100*75.85 - 100*75.83 - 100*75.92 - 100*75.81 - 100*75.96 - 100*75.94 - 100*75.9 -100*75.35 -> -75830 | AA4: =-100*12.94 - 100*12.94 - 100*12.94 - 200*12.94 - 200*12.94 - 200*12.94 - 200*12.94 - 300*12.94 - 600*12.94 - 1000*12.94 - 1000*12.94 - 1500*12.94 -> -71170 | AB4: =-100*49.47 - 100*49.35 -100*51.86 - 100*51.95 - 100*51.95 - 100*51.96 - 100*51.98 - 100*52.01 - 100*52.06 -> -46259 | AC4: =-3*166.18-17*166.18-20*166.23-20*166.29-20*166.34-20*166.38-20*166.39-20*166.54-25*172.34 - 25*172.14 - 25*172.22 -50*156.92 - 50*157.36 -> -51918.5 | AE4: 0 | AF4: 0 | AG4: 0 | AH4: 0 | AI4: =SUM(C4:AH4) -> -843579.73 | AJ4: =SUM(AI3:AI4) -> -494214.01
B5: Rebecimento de proventos (-) | C5: 0 | D5: 0 | E5: 0 | F5: 0 | G5: 0 | H5: 0 | I5: 0 | J5: 0 | K5: 0 | L5: 0 | M5: 0 | N5: 0 | O5: 0 | P5: 0 | Q5: 0 | S5: 0 | T5: 0 | U5: 0 | V5: 0 | W5: 0 | X5: 0 | Y5: 0 | Z5: 0 | AA5: 0 | AB5: 0 | AC5: 0 | AD5: 0 | AE5: 0 | AF5: 0 | AG5: 0 | AH5: 0 | AI5: =SUM(C5:AH5) -> 0 | AJ5: =SUM(AI2:AI5) -> 3129159.4
B6: Valor final no mês | C6: =+(12648.27+20967.15)*0+(12732.53+21106.26)*0+(12753.71+21141.27)*0+(21211.38+12796.6) -> 34007.98 | D6: =+150973.61*0+151566.61*0+151999.69*0+152254.52*0+152757.14 -> 152757.14 | E6: =+((-34158-68280)+(+1593+475-29768+6509))*0+(+4649)*0+((68069.38-14802)+(+794-63403.25))*0+((-23272-18115)-(29197))*0+((+3383.54-18115)+(-29197))*0+((-16940-18127)+(-29197-58481.52))*0+((+35059-18127)+(-29197-58481))*0+((+24450-15988)+(-29197-69781))*0+(-179460-52554)+(-29197-35766-36161) -> -333138 | F6: =+(+400+87+13-500)*145.46 -> 0 | G6: =+114441.83*0+114761.23*0+115075.87*0+115334.66*0+115725.16 -> 115725.16 | H6: =+17230.859*0+16275*0+15710*0+15765*0+5146.48+10424.2 -> 15570.68 | I6: =+188146.5*0+188703.88*0+189306.57*0+189751.27*0+190427.39 -> 190427.39 | J6: =+232459.53*0+233099.7*0+233748.6*0+234265.56*0+235057.83 -> 235057.83 | K6: =+227644.99*0+228399.04*0+230200 -> 230200 | L6: =+59961.56*0+(60202.83+35500-24568)*0+(+68739+17000-15566+10000)*0+(79573.81+5000-14970)*0+69408*0+78973*0+(78572+5000+6000)*0+89303*0+88531*0+89125.92 -> 89125.92 | M6: =+284245+24568+15566+14970 -> 339349 | O6: =+120875.65*0+121168.16*0+121367.79*0+121570.9*0+121859.62 -> 121859.62 | P6: =+229663.28*0+230256.42*0+230660.74*0+230920.8*0+231658.11 -> 231658.11 | Q6: =+62619.35*0+62612.83*0+62649.84*0+63463 -> 63463 | R6: =+(+2850-500-200-200-200-90-60-50)*113.82 -> 176421 | S6: =+(254-200-54)*145.46 -> 0 | T6: 0 | U6: =+(+9845+800+300+763)*71.69 -> 839346.52 | V6: =+(+1700+100-150-500)*94.71 -> 108916.5 | W6: 0 | X6: =+(+410)*159.3 -> 65313 | Y6: 0 | Z6: =+(+1000-900-100)*72.21 -> 0 | AA6: =+(+3400+1100+1000-5500)*13 -> 0 | AB6: =+(+4200-200-700)*51.72 -> 170676 | AC6: =+(+1010-140-75-100)*156.5 -> 108767.5 | AD6: =+450*94.71 -> 42619.5 | AE6: 0 | AF6: =+(+1960+230)*71.62 -> 156847.8 | AG6: 0 | AH6: 0 | AI6: =SUM(C6:AH6) -> 3154971.6 | AJ6: =AJ5-AI6 -> -25812.21 | AO6: "Nasser Family BTG" Investimentos 2026
B7: Rentabilidade (ao mês) | C7: =IFERROR(IF(C6=0,(-C4/C2)-1,C8),"") -> 0.011677974 | D7: =IFERROR(IF(D6=0,(-D4/D2)-1,D8),"") -> 0.011813522 | E7: =IFERROR(IF(E6=0,(-E4/E2)-1,E8),"") -> 0 | F7: =IFERROR(IF(F6=0,(-F4/F2)-1,F8),"") -> 0.25299175 | G7: =IFERROR(IF(G6=0,(-G4/G2)-1,G8),"") -> 0.011772036 | H7: =IFERROR(IF(H6=0,(-H4/H2)-1,H8),"") -> 0.013644874 | I7: =IFERROR(IF(I6=0,(-I4/(I2+I3))-1,I8),"") -> 0.012680295 | J7: =IFERROR(IF(J6=0,(-J4/(J2+J3))-1,J8),"") -> 0.011732957 | K7: =IFERROR(IF(K6=0,(-K4/(K2+K3))-1,K8),"") -> 0.011781185 | L7: =IFERROR(IF(L6=0,(-L4/(L2+L3))-1,L8),"") -> -0.054071426 | M7: =IFERROR(IF(M6=0,(-M4/(M2+M3))-1,M8),"") -> -2.121705e-06 | N7: =IFERROR(IF(N6=0,(-N4/(N2+N3))-1,N8),"") | O7: =IFERROR(IF(O6=0,(-O4/(O2+O3))-1,O8),"") -> 0.0081403492 | P7: =IFERROR(IF(P6=0,(-P4/(P2+P3))-1,P8),"") -> 0.0086858901 | ... AH7: =IFERROR(IF(AH6=0,(-AH4/(AH2+AH3))-1,AH8),"") | AI7: =IFERROR(IF(AI6=0,(-AI4/AI2)-1,AI8),"") -> 0.0082489277 | AJ7: =AI6*AI7 -> 26025.133
B8: Não mexer | C8: =IFERROR(IF(AND(C2<>0,C6=""),"",(C6/(C2+C3+C4+C5))-1),"") -> 0.011677974 | D8: =IFERROR(IF(AND(D2<>0,D6=""),"",(D6/(D2+D3+D4+D5))-1),"") -> 0.011813522 | E8: =IFERROR(IF(AND(E2<>0,E6=""),"",(E6/(E2+E3+E4+E5))-1),"") -> 0 | F8: =IFERROR(IF(AND(F2<>0,F6=""),"",(F6/(F2+F3+F4+F5))-1),"") -> -1 | G8: =IFERROR(IF(AND(G2<>0,G6=""),"",(G6/(G2+G3+G4+G5))-1),"") -> 0.011772036 | H8: =IFERROR(IF(AND(H2<>0,H6=""),"",(H6/(H2+H3+H4+H5))-1),"") -> 0.013644874 | I8: =IFERROR(IF(AND(I2<>0,I6=""),"",(I6/(I2+I3+I4+I5))-1),"") -> 0.012680295 | J8: =IFERROR(IF(AND(J2<>0,J6=""),"",(J6/(J2+J3+J4+J5))-1),"") -> 0.011732957 | ... AI8: =IFERROR(IF(AND(AI2<>0,AI6=""),"",(AI6/(AI2+AI3+AI4+AI5))-1),"") -> 0.0082489277
B9: Ativo/PL | C9: =IFERROR(C6/$AI$6,"") -> 0.010779171 | D9: =IFERROR(D6/$AI$6,"") -> 0.048417912 | E9: =IFERROR(E6/$AI$6,"") -> -0.10559144 | F9: =IFERROR(F6/$AI$6,"") -> 0 | G9: =IFERROR(G6/$AI$6,"") -> 0.036680254 | H9: =IFERROR(H6/$AI$6,"") -> 0.0049352837 | I9: =IFERROR(I6/$AI$6,"") -> 0.060357877 | J9: =IFERROR(J6/$AI$6,"") -> 0.074503944 | ... AI9: =IFERROR(AI6/$AI$6,"") -> 1 | AJ9: =AI6-AI2 -> -468401.8 | AK9: =AI6/AI2-1 -> -0.12927229
A10: 45689 | B10: Valor-base | C10: =IF(C14="","",C6) -> 34007.98 | D10: =IF(D14="","",D6) -> 152757.14 | E10: =IF(E14="","",E6) -> -333138 | F10: =IF(F14="","",F6) -> 0 | G10: =IF(G14="","",G6) -> 115725.16 | H10: =IF(H14="","",H6) -> 15570.68 | I10: =IF(I14="","",I6) -> 190427.39 | J10: =IF(J14="","",J6) -> 235057.83 | ... AH10: =IF(AH14="","",AH6) -> 0 | AI10: =SUM(C10:AH10) -> 3154971.6
B11: Investimento (+) | C11: 0 | D11: 0 | E11: 0 | F11: =+300*147.59 +40*147.75 + 40*147.75 + 1*147.74 + 1*147.74 + 6*147.74 + 11*147.74 + 11*147.74 + 23*147.74 + 27*147.74 + 40*147.74 + 40*147.74 + 13*147.73 + 27*147.73 + 40*147.71 + 40*147.71 + 40*147.71 -> 103369.8 | G11: 0 | H11: 0 | I11: 0 | J11: 0 | K11: 0 | L11: =+10000+10000+15000+10000+5000+12000 -> 62000 | M11: =+20734.59*0+18674.97+9941.48 -> 28616.45 | N11: =+50*39.12 + 50*39.06 + 50*39 + 50*38.93 + 50*38.89 + 50*38.85 + 50*38.81 + 50*38.81 + 50*38.81 + 50*38.68 + 4*38.62 + 46*38.62 + 50*38.61 + 1*38.6 + 49*38.6 + 50*38.55 + 50*38.54 -> 29094 | O11: 0 | P11: 0 | Q11: 0 | R11: =100*120.14 + 100*120.02 + 100*119.81 -> 35997 | S11: =+70*147.89+70*147.92 -> 20706.7 | T11: 0 | U11: =+50*66.9+50*66.88 -> 6689 | V11: =+200*84.65 + 200*85.62 -> 34054 | W11: 0 | X11: =+16*132.03 + 16*132.13 + 16*132.23 + 16*132.33 + 16*132.43 + 16*132.53 + 16*132.65 + 16*132.73 + 16*132.83 + 16*132.93 -> 21197.12 | Y11: 0 | Z11: 0 | AA11: 0 | AB11: 0 | AC11: =+374*131.64 -> 49233.36 | AD11: =+50*84.87 + 50*84.73 + 50*84.65 + 50*83.68 -> 16896.5 | AE11: 0 | AF11: 0 | AG11: 0 | AH11: 0 | AI11: =SUM(C11:AH11) -> 407853.93
B12: Resgate (-) | C12: 0 | D12: 0 | E12: =+E14-E10 -> 262280 | H12: 0 | I12: 0 | J12: 0 | K12: 0 | L12: =-519.15-20734.59-18674.97-9941.48 -> -49870.19 | M12: 0 | N12: 0 | O12: 0 | P12: 0 | Q12: 0 | R12: =-50*108.62 - 50*109.31 - 50*108.06 - 25*109.09 - 60*110.02 - 60*110.1 - 60*110.29 - 60*110.74 - 60*110.47 - 60*111.01-1*125.34 - 1*125.34 - 2*125.34 - 5*125.34 - 7*125.34 - 10*125.34 - 24*125.34 - 50*125.41 - 50*125.47 - 50*125.53 - 50*127.67 - 65*127.78 - 50*127.82 - 50*127.98 -100*129.43 - 13*129.79 - 87*129.79 - 100*129.92 -> -150265.25 | S12: 0 | T12: 0 | U12: 0 | V12: 0 | W12: 0 | X12: 0 | Y12: 0 | Z12: 0 | AA12: 0 | AB12: =-300*53.02 - 300*53.01 - 100*53.01 - 200*53.04 -300*53.02 - 300*53.01 - 100*53.01 - 200*53.04-200*52.42 - 200*52.46 - 200*52.4 - 200*52.42 - 100*52.4 - 100*52.43 - 200*52.47 - 200*52.38 - 200*52.44 - 200*52.41 - 200*52.41 -> -200281 | AC12: =-22*164.11-50*164.13-50*164.18 -> -20025.92 | AD12: 0 | AE12: 0 | AF12: 0 | AG12: 0 | AH12: 0 | AI12: =SUM(C12:AH12) -> -158162.36 | AJ12: =SUM(AI11:AI12) -> 249691.57
B13: Rebecimento de proventos (-) | C13: 0 | D13: 0 | E13: 0 | G13: 0 | H13: 0 | I13: 0 | J13: 0 | K13: 0 | L13: 0 | M13: 0 | N13: 0 | O13: 0 | P13: 0 | Q13: 0 | R13: 0 | S13: 0 | T13: 0 | U13: 0 | V13: 0 | W13: 0 | X13: 0 | Y13: 0 | Z13: 0 | AA13: 0 | AB13: 0 | AC13: 0 | AD13: 0 | AE13: 0 | AF13: 0 | AG13: 0 | AH13: 0 | AI13: =SUM(C13:AH13) -> 0 | AJ13: =SUM(AI10:AI13) -> 3404663.2
B14: Valor final no mês | C14: =+(12810.76+21234.84)*0+(12846.89+21293.51)*0+(+21317.01+12861.07)*0+(21364.24+12889.33) -> 34253.57 | D14: =+152925.14*0+153342.8*0+153511.95*0+153850.98 -> 153850.98 | E14: =+((+32199.68+23410)+(-30192.43-39361.2-35766))*0+((+7194.69+25458)+(-30192.43-39361.2-35766))*0+((-21973+17201.39)+(-35000-30192-37480))*0+((+894-37480-35000-30192)+(+97372+27911-71287-3995))*0+((+26070-2623)+(+894-37480-35000-39159))*0+((+17753-2623)+(-39158-13288-37481+19405)+(+26500+15240))*0+((82846+12549)+(-39158-13288-37481+19405))*0+((+127655-23863)+(+9185-18158-34288-37481))*0+((-23863+70155)+(-39158))*0+((+62999-27643)+(-39158-27532))*0+((+600-5598)+(-18999)+(+13870+38700))*0+((+52566-58781)+(-18899)+(+13870+38700))*0+((+90992-44821)+(-18899))*0+((+90806)+(-24988-15000)+(+3543))*0+((+94226.4+178)+(-24988-15000))*0+(+49726+178)*0+((+29374)+(+2530))*0+(+31998+178)*0+(30657)*0+(19644.02)*0+(+22324+178)*0+(-29428.92+223.79)*0+((-65211+223)+(+4086+10132)+(+2731-22708))*0+(-55191+4310)+(+2731-22708) -> -70858 | F14: =+(+300+400)*148.12 -> 103684 | G14: =+115783*0+116105.09*0+116296.85*0+116489.59*0+116554.34 -> 116554.34 | H14: =+15636*0+15681.96 -> 15681.96 | I14: =+190535.15*0+191038.5*0+191204.15*0+191548.66*0+191652.08 -> 191652.08 | J14: =+235184.58*0+235843.38*0+236112.54*0+236634.81*0+236766.17 -> 236766.17 | K14: =+230295.13*0+230422.09*0+230676.23*0+231057.96*0+231057.96*0+231440.33*0+231695.59 -> 231695.59 | L14: =+89129.32*0+88375*0+97743*0+76306*0+(+76546+10000-18674.97)*0+68069.15*0+(67886+15000-9941.48)*0+72742.08*0+(72646+10000)*0+82802.92*0+83188*0+(+82912+5000)*0+(87668+12000)*0+98858 -> 98858 | M14: =+(339349+20734.59)*0+(+362041.84)+(18674.97+9941.18) -> 390657.99 | N14: =+750*38.87 -> 29152.5 | O14: =+121908.92*0+122155.68*0+122303.96*0+122514.18 -> 122514.18 | P14: =+231758.08*0+232258.6*0+232559.41*0+232860.62*0+232984.34 -> 232984.34 | Q14: =+63656.91*0+63669.16*0+63682.37*0+63978.03 -> 63978.03 | R14: =+(+1550-535-415-300+300)*121.7 -> 73020 | S14: =+(+70+70)*148.12 -> 20736.8 | T14: 0 | U14: =+(+11708+100)*66.92 -> 790191.36 | V14: =+(+1150+400)*87.39 -> 135454.5 | W14: 0 | X14: =+(+410+160)*131.95 -> 75211.5 | Y14: 0 | Z14: 0 | AA14: 0 | AB14: =+(+3300-400-900-2000)*52.4 -> 0 | AC14: =+(+695-122+374)*131.95 -> 124956.65 | AD14: =+(+450+200)*87.37 -> 56790.5 | AE14: 0 | AF14: =+2190*66.92 -> 146554.8 | AG14: 0 | AH14: 0 | AI14: =SUM(C14:AH14) -> 3374341.8 | AJ14: =AJ13-AI14 -> 30321.38
B15: Rentabilidade (ao mês) | C15: =IFERROR(IF(C14=0,(-C12/C10)-1,C16),"") -> 0.0072215404 | D15: =IFERROR(IF(D14=0,(-D12/D10)-1,D16),"") -> 0.0071606473 | E15: =IFERROR(IF(E14=0,(-E12/E10)-1,E16),"") -> 0 | F15: =IFERROR(IF(F14=0,(-F12/F10)-1,F16),"") -> 0.0030395725 | G15: =IFERROR(IF(G14=0,(-G12/G10)-1,G16),"") -> 0.0071650797 | H15: =IFERROR(IF(H14=0,(-H12/H10)-1,H16),"") -> 0.0071467656 | I15: =IFERROR(IF(I14=0,(-I12/I10)-1,I16),"") -> 0.0064312702 | J15: =IFERROR(IF(J14=0,(-J12/J10)-1,J16),"") -> 0.0072677434 | ... AI15: =IFERROR(IF(AI14=0,(-AI12/AI10)-1,AI16),"") -> -0.0089058383 | AJ15: =AI14*AI15 -> -30051.343
B16: Não mexer | C16: =IFERROR(IF(AND(C10<>0,C14=""),"",(C14/(C10+C11+C12+C13))-1),"") -> 0.0072215404 | D16: =IFERROR(IF(AND(D10<>0,D14=""),"",(D14/(D10+D11+D12+D13))-1),"") -> 0.0071606473 | E16: =IFERROR(IF(AND(E10<>0,E14=""),"",(E14/(E10+E11+E12+E13))-1),"") -> 0 | F16: =IFERROR(IF(AND(F10<>0,F14=""),"",(F14/(F10+F11+F12+F13))-1),"") -> 0.0030395725 | G16: =IFERROR(IF(AND(G10<>0,G14=""),"",(G14/(G10+G11+G12+G13))-1),"") -> 0.0071650797 | H16: =IFERROR(IF(AND(H10<>0,H14=""),"",(H14/(H10+H11+H12+H13))-1),"") -> 0.0071467656 | I16: =IFERROR(IF(AND(I10<>0,I14=""),"",(I14/(I10+I11+I12+I13))-1),"") -> 0.0064312702 | J16: =IFERROR(IF(AND(J10<>0,J14=""),"",(J14/(J10+J11+J12+J13))-1),"") -> 0.0072677434 | ... AI16: =IFERROR(IF(AND(AI10<>0,AI14=""),"",(AI14/(AI10+AI11+AI12+AI13))-1),"") -> -0.0089058383
B17: Ativo/PL | C17: =IFERROR(C14/$AI$14,"") -> 0.010151186 | D17: =IFERROR(D14/$AI$14,"") -> 0.045594367 | E17: =IFERROR(E14/$AI$14,"") -> -0.020999058 | F17: =IFERROR(F14/$AI$14,"") -> 0.030727177 | G17: =IFERROR(G14/$AI$14,"") -> 0.034541355 | H17: =IFERROR(H14/$AI$14,"") -> 0.004647413 | I17: =IFERROR(I14/$AI$14,"") -> 0.056796877 | J17: =IFERROR(J14/$AI$14,"") -> 0.070166622 | ... AI17: =IFERROR(AI14/$AI$14,"") -> 1 | AJ17: =AI14-AI10 -> 219370.19 | AK17: =AI14/AI10-1 -> 0.069531588
A18: 45717 | B18: Valor-base | C18: =IF(C22="","",C14) -> 34253.57 | D18: =IF(D22="","",D14) -> 153850.98 | E18: =IF(E22="","",E14) -> -70858 | F18: =IF(F22="","",F14) -> 103684 | G18: =IF(G22="","",G14) -> 116554.34 | H18: =IF(H22="","",H14) -> 15681.96 | I18: =IF(I22="","",I14) -> 191652.08 | J18: =IF(J22="","",J14) -> 236766.17 | ... AH18: =IF(AH22="","",AH14) -> 0 | AI18: =SUM(C18:AH18) -> 3374341.8
B19: Investimento (+) | C19: 0 | D19: 0 | E19: 0 | F19: 0 | G19: 0 | H19: 0 | I19: 0 | J19: 0 | K19: 0 | L19: 0 | M19: 0 | N19: 0 | O19: 0 | P19: 0 | Q19: 0 | R19: 0 | S19: 0 | T19: 0 | U19: 0 | V19: 0 | W19: 0 | X19: 0 | Y19: 0 | Z19: 0 | AA19: 0 | AB19: 0 | AC19: 0 | AD19: 0 | AE19: 0 | AF19: 0 | AG19: 0 | AH19: 0 | AI19: =SUM(C19:AH19) -> 0
B20: Resgate (-) | C20: 0 | D20: 0 | E20: 0 | F20: 0 | G20: 0 | H20: 0 | I20: 0 | J20: 0 | K20: 0 | L20: 0 | M20: 0 | N20: 0 | O20: 0 | P20: 0 | Q20: 0 | R20: 0 | S20: 0 | T20: 0 | U20: 0 | V20: 0 | W20: 0 | X20: 0 | Y20: 0 | Z20: 0 | AA20: 0 | AB20: 0 | AC20: 0 | AD20: 0 | AE20: 0 | AF20: 0 | AG20: 0 | AH20: 0 | AI20: =SUM(C20:AH20) -> 0 | AJ20: =SUM(AI19:AI20) -> 0
B21: Rebecimento de proventos (-) | C21: 0 | D21: 0 | E21: 0 | F21: 0 | G21: 0 | H21: 0 | I21: 0 | J21: 0 | K21: 0 | L21: 0 | M21: 0 | N21: 0 | O21: 0 | P21: 0 | Q21: 0 | R21: 0 | S21: 0 | T21: 0 | U21: 0 | V21: 0 | W21: 0 | X21: 0 | Y21: 0 | Z21: 0 | AA21: 0 | AB21: 0 | AC21: 0 | AD21: 0 | AE21: 0 | AF21: 0 | AG21: 0 | AH21: 0 | AI21: =SUM(C21:AH21) -> 0 | AJ21: =SUM(AI18:AI21) -> 3374341.8
B22: Valor final no mês | C22: 0 | D22: 0 | E22: 0 | F22: 0 | G22: 0 | H22: 0 | I22: 0 | J22: 0 | K22: 0 | L22: 0 | M22: 0 | N22: 0 | O22: 0 | P22: 0 | Q22: 0 | R22: 0 | S22: 0 | T22: 0 | U22: 0 | V22: 0 | W22: 0 | X22: 0 | Y22: 0 | Z22: 0 | AA22: 0 | AB22: 0 | AC22: 0 | AD22: 0 | AE22: 0 | AF22: 0 | AG22: 0 | AH22: 0 | AI22: =SUM(C22:AH22) -> 0 | AJ22: =AJ21-AI22 -> 3374341.8
B23: Rentabilidade (ao mês) | C23: =IFERROR(IF(C22=0,(-C20/C18)-1,C24),"") -> -1 | D23: =IFERROR(IF(D22=0,(-D20/D18)-1,D24),"") -> -1 | E23: =IFERROR(IF(E22=0,(-E20/E18)-1,E24),"") -> -1 | F23: =IFERROR(IF(F22=0,(-F20/F18)-1,F24),"") -> -1 | G23: =IFERROR(IF(G22=0,(-G20/G18)-1,G24),"") -> -1 | H23: =IFERROR(IF(H22=0,(-H20/H18)-1,H24),"") -> -1 | I23: =IFERROR(IF(I22=0,(-I20/I18)-1,I24),"") -> -1 | J23: =IFERROR(IF(J22=0,(-J20/J18)-1,J24),"") -> -1 | ... AI23: =IFERROR(IF(AI22=0,(-AI20/AI18)-1,AI24),"") -> -1 | AJ23: =AI22*AI23 -> 0
B24: Não mexer | C24: =IFERROR(IF(AND(C18<>0,C22=""),"",(C22/(C18+C19+C20+C21))-1),"") -> -1 | D24: =IFERROR(IF(AND(D18<>0,D22=""),"",(D22/(D18+D19+D20+D21))-1),"") -> -1 | E24: =IFERROR(IF(AND(E18<>0,E22=""),"",(E22/(E18+E19+E20+E21))-1),"") -> -1 | F24: =IFERROR(IF(AND(F18<>0,F22=""),"",(F22/(F18+F19+F20+F21))-1),"") -> -1 | G24: =IFERROR(IF(AND(G18<>0,G22=""),"",(G22/(G18+G19+G20+G21))-1),"") -> -1 | H24: =IFERROR(IF(AND(H18<>0,H22=""),"",(H22/(H18+H19+H20+H21))-1),"") -> -1 | I24: =IFERROR(IF(AND(I18<>0,I22=""),"",(I22/(I18+I19+I20+I21))-1),"") -> -1 | J24: =IFERROR(IF(AND(J18<>0,J22=""),"",(J22/(J18+J19+J20+J21))-1),"") -> -1 | ... AI24: =IFERROR(IF(AND(AI18<>0,AI22=""),"",(AI22/(AI18+AI19+AI20+AI21))-1),"") -> -1
B25: Ativo/PL | C25: =IFERROR(C22/$AI$22,"") | D25: =IFERROR(D22/$AI$22,"") | E25: =IFERROR(E22/$AI$22,"") | F25: =IFERROR(F22/$AI$22,"") | G25: =IFERROR(G22/$AI$22,"") | H25: =IFERROR(H22/$AI$22,"") | I25: =IFERROR(I22/$AI$22,"") | J25: =IFERROR(J22/$AI$22,"") | ... AI25: =IFERROR(AI22/$AI$22,"") | AJ25: =AI22-AI18 -> -3374341.8 | AK25: =AI22/AI18-1 -> -1
A26: 45748 | B26: Valor-base | C26: =IF(C30="","",C22) -> 0 | D26: =IF(D30="","",D22) -> 0 | E26: =IF(E30="","",E22) -> 0 | F26: =IF(F30="","",F22) -> 0 | G26: =IF(G30="","",G22) -> 0 | H26: =IF(H30="","",H22) -> 0 | I26: =IF(I30="","",I22) -> 0 | J26: =IF(J30="","",J22) -> 0 | ... AH26: =IF(AH30="","",AH22) -> 0 | AI26: =SUM(C26:AH26) -> 0
B27: Investimento (+) | C27: 0 | D27: 0 | E27: 0 | F27: 0 | G27: 0 | H27: 0 | I27: 0 | J27: 0 | K27: 0 | L27: 0 | M27: 0 | N27: 0 | O27: 0 | P27: 0 | Q27: 0 | R27: 0 | S27: 0 | T27: 0 | U27: 0 | V27: 0 | W27: 0 | X27: 0 | Y27: 0 | Z27: 0 | AA27: 0 | AB27: 0 | AC27: 0 | AD27: 0 | AE27: 0 | AF27: 0 | AG27: 0 | AH27: 0 | AI27: =SUM(C27:AH27) -> 0
B28: Resgate (-) | C28: 0 | D28: 0 | E28: 0 | F28: 0 | G28: 0 | H28: 0 | I28: 0 | J28: 0 | K28: 0 | L28: 0 | M28: 0 | N28: 0 | O28: 0 | P28: 0 | Q28: 0 | R28: 0 | S28: 0 | T28: 0 | U28: 0 | V28: 0 | W28: 0 | X28: 0 | Y28: 0 | Z28: 0 | AA28: 0 | AB28: 0 | AC28: 0 | AD28: 0 | AE28: 0 | AF28: 0 | AG28: 0 | AH28: 0 | AI28: =SUM(C28:AH28) -> 0
B29: Rebecimento de proventos (-) | C29: 0 | D29: 0 | E29: 0 | F29: 0 | G29: 0 | H29: 0 | I29: 0 | J29: 0 | K29: 0 | L29: 0 | M29: 0 | N29: 0 | O29: 0 | P29: 0 | Q29: 0 | R29: 0 | S29: 0 | T29: 0 | U29: 0 | V29: 0 | W29: 0 | X29: 0 | Y29: 0 | Z29: 0 | AA29: 0 | AB29: 0 | AC29: 0 | AD29: 0 | AE29: 0 | AF29: 0 | AG29: 0 | AH29: 0 | AI29: =SUM(C29:AH29) -> 0 | AJ29: =SUM(AI26:AI29) -> 0
B30: Valor final no mês | C30: 0 | D30: 0 | E30: 0 | F30: 0 | G30: 0 | H30: 0 | I30: 0 | J30: 0 | K30: 0 | L30: 0 | M30: 0 | N30: 0 | O30: 0 | P30: 0 | Q30: 0 | R30: 0 | S30: 0 | T30: 0 | U30: 0 | V30: 0 | W30: 0 | X30: 0 | Y30: 0 | Z30: 0 | AA30: 0 | AB30: 0 | AC30: 0 | AD30: 0 | AE30: 0 | AF30: 0 | AG30: 0 | AH30: 0 | AI30: =SUM(C30:AH30) -> 0 | AJ30: =AJ29-AI30 -> 0
B31: Rentabilidade (ao mês) | C31: =IFERROR(IF(C30=0,(-C28/C26)-1,C32),"") | D31: =IFERROR(IF(D30=0,(-D28/D26)-1,D32),"") | E31: =IFERROR(IF(E30=0,(-E28/E26)-1,E32),"") | F31: =IFERROR(IF(F30=0,(-F28/F26)-1,F32),"") | G31: =IFERROR(IF(G30=0,(-G28/G26)-1,G32),"") | H31: =IFERROR(IF(H30=0,(-H28/H26)-1,H32),"") | I31: =IFERROR(IF(I30=0,(-I28/I26)-1,I32),"") | J31: =IFERROR(IF(J30=0,(-J28/J26)-1,J32),"") | ... AI31: =IFERROR(IF(AI30=0,(-AI28/AI26)-1,AI32),"") | AJ31: =AI30*AI31 -> 0
B32: Não mexer | C32: =IFERROR(IF(AND(C26<>0,C30=""),"",(C30/(C26+C27+C28+C29))-1),"") | D32: =IFERROR(IF(AND(D26<>0,D30=""),"",(D30/(D26+D27+D28+D29))-1),"") | E32: =IFERROR(IF(AND(E26<>0,E30=""),"",(E30/(E26+E27+E28+E29))-1),"") | F32: =IFERROR(IF(AND(F26<>0,F30=""),"",(F30/(F26+F27+F28+F29))-1),"") | G32: =IFERROR(IF(AND(G26<>0,G30=""),"",(G30/(G26+G27+G28+G29))-1),"") | H32: =IFERROR(IF(AND(H26<>0,H30=""),"",(H30/(H26+H27+H28+H29))-1),"") | I32: =IFERROR(IF(AND(I26<>0,I30=""),"",(I30/(I26+I27+I28+I29))-1),"") | J32: =IFERROR(IF(AND(J26<>0,J30=""),"",(J30/(J26+J27+J28+J29))-1),"") | ... AI32: =IFERROR(IF(AND(AI26<>0,AI30=""),"",(AI30/(AI26+AI27+AI28+AI29))-1),"")
B33: Ativo/PL | C33: =IFERROR(C30/$AI$30,"") | D33: =IFERROR(D30/$AI$30,"") | E33: =IFERROR(E30/$AI$30,"") | F33: =IFERROR(F30/$AI$30,"") | G33: =IFERROR(G30/$AI$30,"") | H33: =IFERROR(H30/$AI$30,"") | I33: =IFERROR(I30/$AI$30,"") | J33: =IFERROR(J30/$AI$30,"") | ... AI33: =IFERROR(AI30/$AI$30,"") | AJ33: =AI30-AI26 -> 0 | AK33: =AI30/AI26-1 -> #DIV/0!
A34: 45778 | B34: Valor-base | C34: =IF(C38="","",C30) -> 0 | D34: =IF(D38="","",D30) -> 0 | E34: =IF(E38="","",E30) -> 0 | F34: =IF(F38="","",F30) -> 0 | G34: =IF(G38="","",G30) -> 0 | H34: =IF(H38="","",H30) -> 0 | I34: =IF(I38="","",I30) -> 0 | J34: =IF(J38="","",J30) -> 0 | ... AH34: =IF(AH38="","",AH30) -> 0 | AI34: =SUM(C34:AH34) -> 0
B35: Investimento (+) | C35: 0 | D35: 0 | E35: 0 | F35: 0 | G35: 0 | H35: 0 | I35: 0 | J35: 0 | K35: 0 | L35: 0 | M35: 0 | N35: 0 | O35: 0 | P35: 0 | Q35: 0 | R35: 0 | S35: 0 | T35: 0 | U35: 0 | V35: 0 | W35: 0 | X35: 0 | Y35: 0 | Z35: 0 | AA35: 0 | AB35: 0 | AC35: 0 | AD35: 0 | AE35: 0 | AF35: 0 | AG35: 0 | AH35: 0 | AI35: =SUM(C35:AH35) -> 0
B36: Resgate (-) | C36: 0 | D36: 0 | E36: 0 | F36: 0 | G36: 0 | H36: 0 | I36: 0 | J36: 0 | K36: 0 | L36: 0 | M36: 0 | N36: 0 | O36: 0 | P36: 0 | Q36: 0 | R36: 0 | S36: 0 | T36: 0 | U36: 0 | V36: 0 | W36: 0 | X36: 0 | Y36: 0 | Z36: 0 | AA36: 0 | AB36: 0 | AC36: 0 | AD36: 0 | AE36: 0 | AF36: 0 | AG36: 0 | AH36: 0 | AI36: =SUM(C36:AH36) -> 0
B37: Rebecimento de proventos (-) | C37: 0 | D37: 0 | E37: 0 | F37: 0 | G37: 0 | H37: 0 | I37: 0 | J37: 0 | K37: 0 | L37: 0 | M37: 0 | N37: 0 | O37: 0 | P37: 0 | Q37: 0 | R37: 0 | S37: 0 | T37: 0 | U37: 0 | V37: 0 | W37: 0 | X37: 0 | Y37: 0 | Z37: 0 | AA37: 0 | AB37: 0 | AC37: 0 | AD37: 0 | AE37: 0 | AF37: 0 | AG37: 0 | AH37: 0 | AI37: =SUM(C37:AH37) -> 0 | AJ37: =SUM(AI34:AI37) -> 0
B38: Valor final no mês | C38: 0 | D38: 0 | E38: 0 | F38: 0 | G38: 0 | H38: 0 | I38: 0 | J38: 0 | K38: 0 | L38: 0 | M38: 0 | N38: 0 | O38: 0 | P38: 0 | Q38: 0 | R38: 0 | S38: 0 | T38: 0 | U38: 0 | V38: 0 | W38: 0 | X38: 0 | Y38: 0 | Z38: 0 | AA38: 0 | AB38: 0 | AC38: 0 | AD38: 0 | AE38: 0 | AF38: 0 | AG38: 0 | AH38: 0 | AI38: =SUM(C38:AH38) -> 0 | AJ38: =AJ37-AI38 -> 0
B39: Rentabilidade (ao mês) | C39: =IFERROR(IF(C38=0,(-C36/C34)-1,C40),"") | D39: =IFERROR(IF(D38=0,(-D36/D34)-1,D40),"") | E39: =IFERROR(IF(E38=0,(-E36/E34)-1,E40),"") | F39: =IFERROR(IF(F38=0,(-F36/F35)-1,F40),"") | G39: =IFERROR(IF(G38=0,(-G36/G34)-1,G40),"") | H39: =IFERROR(IF(H38=0,(-H36/H34)-1,H40),"") | I39: =IFERROR(IF(I38=0,(-I36/I34)-1,I40),"") | J39: =IFERROR(IF(J38=0,(-J36/J34)-1,J40),"") | K39: =IFERROR(IF(K38=0,(-K36/K34)-1,K40),"") | L39: =IFERROR(IF(L38=0,(-L36/L34)-1,L40),"") | M39: =IFERROR(IF(M38=0,(-M36/M34)-1,M40),"") | N39: =IFERROR(IF(N38=0,(-N36/N34)-1,N40),"") | ... AF39: =IFERROR(IF(AF38=0,(-AF36/AF34)-1,AF40),"") | AG39: =IFERROR(IF(AG38=0,(-AG36/AG35)-1,AG40),"") | AH39: =IFERROR(IF(AH38=0,(-AH36/AH34)-1,AH40),"") | AI39: =IFERROR(IF(AI38=0,(-AI36/AI34)-1,AI40),"") | AJ39: =AI38*AI39 -> 0
B40: Não mexer | C40: =IFERROR(IF(AND(C34<>0,C38=""),"",(C38/(C34+C35+C36+C37))-1),"") | D40: =IFERROR(IF(AND(D34<>0,D38=""),"",(D38/(D34+D35+D36+D37))-1),"") | E40: =IFERROR(IF(AND(E34<>0,E38=""),"",(E38/(E34+E35+E36+E37))-1),"") | F40: =IFERROR(IF(AND(F34<>0,F38=""),"",(F38/(F34+F35+F36+F37))-1),"") | G40: =IFERROR(IF(AND(G34<>0,G38=""),"",(G38/(G34+G35+G36+G37))-1),"") | H40: =IFERROR(IF(AND(H34<>0,H38=""),"",(H38/(H34+H35+H36+H37))-1),"") | I40: =IFERROR(IF(AND(I34<>0,I38=""),"",(I38/(I34+I35+I36+I37))-1),"") | J40: =IFERROR(IF(AND(J34<>0,J38=""),"",(J38/(J34+J35+J36+J37))-1),"") | ... AI40: =IFERROR(IF(AND(AI34<>0,AI38=""),"",(AI38/(AI34+AI35+AI36+AI37))-1),"")
B41: Ativo/PL | C41: =IFERROR(C38/$AI$38,"") | D41: =IFERROR(D38/$AI$38,"") | E41: =IFERROR(E38/$AI$38,"") | F41: =IFERROR(F38/$AI$38,"") | G41: =IFERROR(G38/$AI$38,"") | H41: =IFERROR(H38/$AI$38,"") | I41: =IFERROR(I38/$AI$38,"") | J41: =IFERROR(J38/$AI$38,"") | ... AI41: =IFERROR(AI38/$AI$38,"") | AJ41: =AI38-AI34 -> 0 | AK41: =AI38/AI34-1 -> #DIV/0!
A42: 45809 | B42: Valor-base | C42: =IF(C46="","",C38) -> 0 | D42: =IF(D46="","",D38) -> 0 | E42: =IF(E46="","",E38) -> 0 | F42: =IF(F46="","",F38) -> 0 | G42: =IF(G46="","",G38) -> 0 | H42: =IF(H46="","",H38) -> 0 | I42: =IF(I46="","",I38) -> 0 | J42: =IF(J46="","",J38) -> 0 | ... AH42: =IF(AH46="","",AH38) -> 0 | AI42: =SUM(C42:AH42) -> 0
B43: Investimento (+) | C43: 0 | D43: 0 | E43: 0 | F43: 0 | G43: 0 | H43: 0 | I43: 0 | J43: 0 | K43: 0 | L43: 0 | M43: 0 | N43: 0 | O43: 0 | P43: 0 | Q43: 0 | R43: 0 | S43: 0 | T43: 0 | U43: 0 | V43: 0 | W43: 0 | X43: 0 | Y43: 0 | Z43: 0 | AA43: 0 | AB43: 0 | AC43: 0 | AD43: 0 | AE43: 0 | AF43: 0 | AG43: 0 | AH43: 0 | AI43: =SUM(C43:AH43) -> 0
B44: Resgate (-) | C44: 0 | D44: 0 | E44: 0 | F44: 0 | G44: 0 | H44: 0 | I44: 0 | J44: 0 | K44: 0 | L44: 0 | M44: 0 | N44: 0 | O44: 0 | P44: 0 | Q44: 0 | R44: 0 | S44: 0 | T44: 0 | U44: 0 | V44: 0 | W44: 0 | X44: 0 | Y44: 0 | Z44: 0 | AA44: 0 | AB44: 0 | AC44: 0 | AD44: 0 | AE44: 0 | AF44: 0 | AG44: 0 | AH44: 0 | AI44: =SUM(C44:AH44) -> 0
B45: Rebecimento de proventos (-) | C45: 0 | D45: 0 | E45: 0 | F45: 0 | G45: 0 | H45: 0 | I45: 0 | J45: 0 | K45: 0 | L45: 0 | M45: 0 | N45: 0 | O45: 0 | P45: 0 | Q45: 0 | R45: 0 | S45: 0 | T45: 0 | U45: 0 | V45: 0 | W45: 0 | X45: 0 | Y45: 0 | Z45: 0 | AA45: 0 | AB45: 0 | AC45: 0 | AD45: 0 | AE45: 0 | AF45: 0 | AG45: 0 | AH45: 0 | AI45: =SUM(C45:AH45) -> 0 | AJ45: =SUM(AI42:AI44) -> 0 | AN45: QUADRO-RESUMO
B46: Valor final no mês | C46: 0 | D46: 0 | E46: 0 | F46: 0 | G46: 0 | H46: 0 | I46: 0 | J46: 0 | K46: 0 | L46: 0 | M46: 0 | N46: 0 | O46: 0 | P46: 0 | Q46: 0 | R46: 0 | S46: 0 | T46: 0 | U46: 0 | V46: 0 | W46: 0 | X46: 0 | Y46: 0 | Z46: 0 | AA46: 0 | AB46: 0 | AC46: 0 | AD46: 0 | AE46: 0 | AF46: 0 | AG46: 0 | AH46: 0 | AI46: =SUM(C46:AH46) -> 0 | AJ46: =AJ45-AI46 -> 0
B47: Rentabilidade (ao mês) | C47: =IFERROR(IF(C46=0,(-C44/C42)-1,C48),"") | D47: =IFERROR(IF(D46=0,(-D44/D42)-1,D48),"") | E47: =IFERROR(IF(E46=0,(-E44/E42)-1,E48),"") | F47: =IFERROR(IF(F46=0,(-F44/F42)-1,F48),"") | G47: =IFERROR(IF(G46=0,(-G44/G42)-1,G48),"") | H47: =IFERROR(IF(H46=0,(-H44/H42)-1,H48),"") | I47: =IFERROR(IF(I46=0,(-I44/I42)-1,I48),"") | J47: =IFERROR(IF(J46=0,(-J44/J42)-1,J48),"") | ... AI47: =IFERROR(IF(AI46=0,(-AI44/AI42)-1,AI48),"") | AJ47: =AI46*AI47 -> 0 | AN47: Valor da carteira | AP47: =IF(AI94=0,IF(AI86=0,IF(AI78=0,IF(AI70=0,IF(AI62=0,IF(AI54=0,IF(AI46=0,IF(AI38=0,IF(AI30=0,IF(AI22=0,IF(AI14=0,AI6,AI14),AI22),AI30),AI38),AI46),AI54),AI62),AI70),AI78),AI86),AI94) -> 3374341.8
B48: Não mexer | C48: =IFERROR(IF(AND(C42<>0,C46=""),"",(C46/(C42+C43+C44+C45))-1),"") | D48: =IFERROR(IF(AND(D42<>0,D46=""),"",(D46/(D42+D43+D44+D45))-1),"") | E48: =IFERROR(IF(AND(E42<>0,E46=""),"",(E46/(E42+E43+E44+E45))-1),"") | F48: =IFERROR(IF(AND(F42<>0,F46=""),"",(F46/(F42+F43+F44+F45))-1),"") | G48: =IFERROR(IF(AND(G42<>0,G46=""),"",(G46/(G42+G43+G44+G45))-1),"") | H48: =IFERROR(IF(AND(H42<>0,H46=""),"",(H46/(H42+H43+H44+H45))-1),"") | I48: =IFERROR(IF(AND(I42<>0,I46=""),"",(I46/(I42+I43+I44+I45))-1),"") | J48: =IFERROR(IF(AND(J42<>0,J46=""),"",(J46/(J42+J43+J44+J45))-1),"") | ... AI48: =IFERROR(IF(AND(AI42<>0,AI46=""),"",(AI46/(AI42+AI43+AI44+AI45))-1),"")
B49: Ativo/PL | C49: =IFERROR(C46/$AI$46,"") | D49: =IFERROR(D46/$AI$46,"") | E49: =IFERROR(E46/$AI$46,"") | F49: =IFERROR(F46/$AI$46,"") | G49: =IFERROR(G46/$AI$46,"") | H49: =IFERROR(H46/$AI$46,"") | I49: =IFERROR(I46/$AI$46,"") | J49: =IFERROR(J46/$AI$46,"") | ... AI49: =IFERROR(AI46/$AI$46,"") | AJ49: =AI46-AI42 -> 0 | AK49: =AI46/AI42-1 -> #DIV/0!
A50: 45839 | B50: Valor-base | C50: =IF(C54="","",C46) -> 0 | D50: =IF(D54="","",D46) -> 0 | E50: =IF(E54="","",E46) -> 0 | F50: =IF(F54="","",F46) -> 0 | G50: =IF(G54="","",G46) -> 0 | H50: =IF(H54="","",H46) -> 0 | I50: =IF(I54="","",I46) -> 0 | J50: =IF(J54="","",J46) -> 0 | ... AH50: =IF(AH54="","",AH46) -> 0 | AI50: =SUM(C50:AH50) -> 0
B51: Investimento (+) | C51: 0 | D51: 0 | E51: 0 | F51: 0 | G51: 0 | H51: 0 | I51: 0 | J51: 0 | K51: 0 | L51: 0 | M51: 0 | N51: 0 | O51: 0 | P51: 0 | Q51: 0 | R51: 0 | S51: 0 | T51: 0 | U51: 0 | V51: 0 | W51: 0 | X51: 0 | Y51: 0 | Z51: 0 | AA51: 0 | AB51: 0 | AC51: 0 | AD51: 0 | AE51: 0 | AF51: 0 | AG51: 0 | AH51: 0 | AI51: =SUM(C51:AH51) -> 0 | AN51: Rendimento (no ano) | AP51: =AN74 -> -0.00073037418
B52: Resgate (-) | C52: 0 | D52: 0 | E52: 0 | F52: 0 | G52: 0 | H52: 0 | I52: 0 | J52: 0 | K52: 0 | L52: 0 | M52: 0 | N52: 0 | O52: 0 | P52: 0 | Q52: 0 | R52: 0 | S52: 0 | T52: 0 | U52: 0 | V52: 0 | W52: 0 | X52: 0 | Y52: 0 | Z52: 0 | AA52: 0 | AB52: 0 | AC52: 0 | AD52: 0 | AE52: 0 | AF52: 0 | AG52: 0 | AH52: 0 | AI52: =SUM(C52:AH52) -> 0 | AR52: =AP47*AP51 -> -2464.5322
B53: Rebecimento de proventos (-) | C53: 0 | D53: 0 | E53: 0 | F53: 0 | G53: 0 | H53: 0 | I53: 0 | J53: 0 | K53: 0 | L53: 0 | M53: 0 | N53: 0 | O53: 0 | P53: 0 | Q53: 0 | R53: 0 | S53: 0 | T53: 0 | U53: 0 | V53: 0 | W53: 0 | X53: 0 | Y53: 0 | Z53: 0 | AA53: 0 | AB53: 0 | AC53: 0 | AD53: 0 | AE53: 0 | AF53: 0 | AG53: 0 | AH53: 0 | AI53: =SUM(C53:AH53) -> 0 | AJ53: =SUM(AI50:AI53) -> 0
B54: Valor final no mês | C54: 0 | D54: 0 | E54: 0 | F54: 0 | G54: 0 | H54: 0 | I54: 0 | J54: 0 | K54: 0 | L54: 0 | M54: 0 | N54: 0 | O54: 0 | P54: 0 | Q54: 0 | R54: 0 | S54: 0 | T54: 0 | U54: 0 | V54: 0 | W54: 0 | X54: 0 | Y54: 0 | Z54: 0 | AA54: 0 | AB54: 0 | AC54: 0 | AD54: 0 | AE54: 0 | AF54: 0 | AG54: 0 | AH54: 0 | AI54: =SUM(C54:AH54) -> 0 | AJ54: =AJ53-AI54 -> 0
B55: Rentabilidade (ao mês) | C55: =IFERROR(IF(C54=0,(-C52/C50)-1,C56),"") | D55: =IFERROR(IF(D54=0,(-D52/D50)-1,D56),"") | E55: =IFERROR(IF(E54=0,(-E52/E50)-1,E56),"") | F55: =IFERROR(IF(F54=0,(-F52/F50)-1,F56),"") | G55: =IFERROR(IF(G54=0,(-G52/G50)-1,G56),"") | H55: =IFERROR(IF(H54=0,(-H52/H50)-1,H56),"") | I55: =IFERROR(IF(I54=0,(-I52/I50)-1,I56),"") | J55: =IFERROR(IF(J54=0,(-J52/J50)-1,J56),"") | ... AI55: =IFERROR(IF(AI54=0,(-AI52/AI50)-1,AI56),"") | AJ55: =AI54*AI55 -> 0
B56: Não mexer | C56: =IFERROR(IF(AND(C50<>0,C54=""),"",(C54/(C50+C51+C52+C53))-1),"") | D56: =IFERROR(IF(AND(D50<>0,D54=""),"",(D54/(D50+D51+D52+D53))-1),"") | E56: =IFERROR(IF(AND(E50<>0,E54=""),"",(E54/(E50+E51+E52+E53))-1),"") | F56: =IFERROR(IF(AND(F50<>0,F54=""),"",(F54/(F50+F51+F52+F53))-1),"") | G56: =IFERROR(IF(AND(G50<>0,G54=""),"",(G54/(G50+G51+G52+G53))-1),"") | H56: =IFERROR(IF(AND(H50<>0,H54=""),"",(H54/(H50+H51+H52+H53))-1),"") | I56: =IFERROR(IF(AND(I50<>0,I54=""),"",(I54/(I50+I51+I52+I53))-1),"") | J56: =IFERROR(IF(AND(J50<>0,J54=""),"",(J54/(J50+J51+J52+J53))-1),"") | ... AI56: =IFERROR(IF(AND(AI50<>0,AI54=""),"",(AI54/(AI50+AI51+AI52+AI53))-1),"")
B57: Ativo/PL | C57: =IFERROR(C54/$AI$54,"") | D57: =IFERROR(D54/$AI$54,"") | E57: =IFERROR(E54/$AI$54,"") | F57: =IFERROR(F54/$AI$54,"") | G57: =IFERROR(G54/$AI$54,"") | H57: =IFERROR(H54/$AI$54,"") | I57: =IFERROR(I54/$AI$54,"") | J57: =IFERROR(J54/$AI$54,"") | ... AI57: =IFERROR(AI54/$AI$54,"") | AJ57: =AI54-AI50 -> 0 | AK57: =AI54/AI50-1 -> #DIV/0!
A58: 45870 | B58: Valor-base | C58: =IF(C62="","",C54) -> 0 | D58: =IF(D62="","",D54) -> 0 | E58: =IF(E62="","",E54) -> 0 | F58: =IF(F62="","",F54) -> 0 | G58: =IF(G62="","",G54) -> 0 | H58: =IF(H62="","",H54) -> 0 | I58: =IF(I62="","",I54) -> 0 | J58: =IF(J62="","",J54) -> 0 | ... AH58: =IF(AH62="","",AH54) -> 0 | AI58: =SUM(C58:AH58) -> 0
B59: Investimento (+) | C59: 0 | D59: 0 | E59: 0 | F59: 0 | G59: 0 | H59: 0 | I59: 0 | J59: 0 | K59: 0 | L59: 0 | M59: 0 | N59: 0 | O59: 0 | P59: 0 | Q59: 0 | R59: 0 | S59: 0 | T59: 0 | U59: 0 | V59: 0 | W59: 0 | X59: 0 | Y59: 0 | Z59: 0 | AA59: 0 | AB59: 0 | AC59: 0 | AD59: 0 | AE59: 0 | AF59: 0 | AG59: 0 | AH59: 0 | AI59: =SUM(C59:AH59) -> 0 | AO59: Carteira "Nasser Family" BTG Investimentos
B60: Resgate (-) | C60: 0 | D60: 0 | E60: 0 | F60: 0 | G60: 0 | H60: 0 | I60: 0 | J60: 0 | K60: 0 | L60: 0 | M60: 0 | N60: 0 | O60: 0 | P60: 0 | Q60: 0 | R60: 0 | S60: 0 | T60: 0 | U60: 0 | V60: 0 | W60: 0 | X60: 0 | Y60: 0 | Z60: 0 | AA60: 0 | AB60: 0 | AC60: 0 | AD60: 0 | AE60: 0 | AF60: 0 | AG60: 0 | AH60: 0 | AI60: =SUM(C60:AH60) -> 0
B61: Rebecimento de proventos (-) | C61: 0 | D61: 0 | E61: 0 | F61: 0 | G61: 0 | H61: 0 | I61: 0 | J61: 0 | K61: 0 | L61: 0 | M61: 0 | N61: 0 | O61: 0 | P61: 0 | Q61: 0 | R61: 0 | S61: 0 | T61: 0 | U61: 0 | V61: 0 | W61: 0 | X61: 0 | Y61: 0 | Z61: 0 | AA61: 0 | AB61: 0 | AC61: 0 | AD61: 0 | AE61: 0 | AF61: 0 | AG61: 0 | AH61: 0 | AI61: =SUM(C61:AH61) -> 0 | AJ61: =SUM(AI58:AI61) -> 0
B62: Valor final no mês | C62: 0 | D62: 0 | E62: 0 | F62: 0 | G62: 0 | H62: 0 | I62: 0 | J62: 0 | K62: 0 | L62: 0 | M62: 0 | N62: 0 | O62: 0 | P62: 0 | Q62: 0 | R62: 0 | S62: 0 | T62: 0 | U62: 0 | V62: 0 | W62: 0 | X62: 0 | Y62: 0 | Z62: 0 | AA62: 0 | AB62: 0 | AC62: 0 | AD62: 0 | AE62: 0 | AF62: 0 | AG62: 0 | AH62: 0 | AI62: =SUM(C62:AH62) -> 0 | AJ62: =AJ61-AI62 -> 0
B63: Rentabilidade (ao mês) | C63: =IFERROR(IF(C62=0,(-C60/C58)-1,C64),"") | D63: =IFERROR(IF(D62=0,(-D60/D58)-1,D64),"") | E63: =IFERROR(IF(E62=0,(-E60/E58)-1,E64),"") | F63: =IFERROR(IF(F62=0,(-F60/F58)-1,F64),"") | G63: =IFERROR(IF(G62=0,(-G60/G58)-1,G64),"") | H63: =IFERROR(IF(H62=0,(-H60/H58)-1,H64),"") | I63: =IFERROR(IF(I62=0,(-I60/I58)-1,I64),"") | J63: =IFERROR(IF(J62=0,(-J60/J58)-1,J64),"") | ... AI63: =IFERROR(IF(AI62=0,(-AI60/AI58)-1,AI64),"") | AJ63: =AI62*AI63 -> 0 | AM63: Evolução do retorno da carteira (mês a mês)
B64: Não mexer | C64: =IFERROR(IF(AND(C58<>0,C62=""),"",(C62/(C58+C59+C60+C61))-1),"") | D64: =IFERROR(IF(AND(D58<>0,D62=""),"",(D62/(D58+D59+D60+D61))-1),"") | E64: =IFERROR(IF(AND(E58<>0,E62=""),"",(E62/(E58+E59+E60+E61))-1),"") | F64: =IFERROR(IF(AND(F58<>0,F62=""),"",(F62/(F58+F59+F60+F61))-1),"") | G64: =IFERROR(IF(AND(G58<>0,G62=""),"",(G62/(G58+G59+G60+G61))-1),"") | H64: =IFERROR(IF(AND(H58<>0,H62=""),"",(H62/(H58+H59+H60+H61))-1),"") | I64: =IFERROR(IF(AND(I58<>0,I62=""),"",(I62/(I58+I59+I60+I61))-1),"") | J64: =IFERROR(IF(AND(J58<>0,J62=""),"",(J62/(J58+J59+J60+J61))-1),"") | ... AI64: =IFERROR(IF(AND(AI58<>0,AI62=""),"",(AI62/(AI58+AI59+AI60+AI61))-1),"")
B65: Ativo/PL | C65: =IFERROR(C62/$AI$62,"") | D65: =IFERROR(D62/$AI$62,"") | E65: =IFERROR(E62/$AI$62,"") | F65: =IFERROR(F62/$AI$62,"") | G65: =IFERROR(G62/$AI$62,"") | H65: =IFERROR(H62/$AI$62,"") | I65: =IFERROR(I62/$AI$62,"") | J65: =IFERROR(J62/$AI$62,"") | ... AI65: =IFERROR(AI62/$AI$62,"") | AJ65: =AI62-AI58 -> 0 | AK65: =AI62/AI58-1 -> #DIV/0!
A66: 45901 | B66: Valor-base | C66: =IF(C70="","",C62) -> 0 | D66: =IF(D70="","",D62) -> 0 | E66: =IF(E70="","",E62) -> 0 | F66: =IF(F70="","",F62) -> 0 | G66: =IF(G70="","",G62) -> 0 | H66: =IF(H70="","",H62) -> 0 | I66: =IF(I70="","",I62) -> 0 | J66: =IF(J70="","",J62) -> 0 | ... AH66: =IF(AH70="","",AH62) -> 0 | AI66: =SUM(C66:AH66) -> 0 | AM66: =IF(AM67="","",A2) -> 45658 | AN66: =IF(AN67="","",A10) -> 45689 | AO66: =IF(AO67="","",A18) -> 45717 | AP66: =IF(AP67="","",A26) | AQ66: =IF(AQ67="","",A34) | AR66: =IF(AR67="","",A42) | AS66: =IF(AS67="","",A50) | AT66: =IF(AT67="","",A58) | AU66: =IF(AU67="","",A66) | AV66: =IF(AV67="","",A74) | AW66: =IF(AW67="","",A82) | AX66: =IF(AX67="","",A90)
B67: Investimento (+) | C67: 0 | D67: 0 | E67: 0 | F67: 0 | G67: 0 | H67: 0 | I67: 0 | J67: 0 | K67: 0 | L67: 0 | M67: 0 | N67: 0 | O67: 0 | P67: 0 | Q67: 0 | R67: 0 | S67: 0 | T67: 0 | U67: 0 | V67: 0 | W67: 0 | X67: 0 | Y67: 0 | Z67: 0 | AA67: 0 | AB67: 0 | AC67: 0 | AD67: 0 | AE67: 0 | AF67: 0 | AG67: 0 | AH67: 0 | AI67: =SUM(C67:AH67) -> 0 | AM67: =AI7 -> 0.0082489277 | AN67: =AI15 -> -0.0089058383 | AO67: =AI23 -> -1 | AP67: =AI31 | AQ67: =AI39 | AR67: =AI47 | AS67: =AI55 | AT67: =AI63 | AU67: =AI71 | AV67: =AI79 | AW67: =AI87 | AX67: =AI95
B68: Resgate (-) | C68: 0 | D68: 0 | E68: 0 | F68: 0 | G68: 0 | H68: 0 | I68: 0 | J68: 0 | K68: 0 | L68: 0 | M68: 0 | N68: 0 | O68: 0 | P68: 0 | Q68: 0 | R68: 0 | S68: 0 | T68: 0 | U68: 0 | V68: 0 | W68: 0 | X68: 0 | Y68: 0 | Z68: 0 | AA68: 0 | AB68: 0 | AC68: 0 | AD68: 0 | AE68: 0 | AF68: 0 | AG68: 0 | AH68: 0 | AI68: =SUM(C68:AH68) -> 0 | AM68: =AI6*AI7 -> 26025.133 | AN68: =AI14*AI15 -> -30051.343 | AO68: =AI22*AI23 -> 0 | AP68: =AI31*AI30 -> 0 | AQ68: =AI38*AI39 -> 0 | AR68: =AI46*AI47 -> 0 | AS68: =AI54*AI55 -> 0 | AT68: =AI62*AI63 -> 0 | AU68: =AI70*AI71 -> 0 | AV68: =AJ79 -> 0 | AW68: =AJ87 -> 0 | AX68: =AJ95 -> 0
B69: Rebecimento de proventos (-) | C69: 0 | D69: 0 | E69: 0 | F69: 0 | G69: 0 | H69: 0 | I69: 0 | J69: 0 | K69: 0 | L69: 0 | M69: 0 | N69: 0 | O69: 0 | P69: 0 | Q69: 0 | R69: 0 | S69: 0 | T69: 0 | U69: 0 | V69: 0 | W69: 0 | X69: 0 | Y69: 0 | Z69: 0 | AA69: 0 | AB69: 0 | AC69: 0 | AD69: 0 | AE69: 0 | AF69: 0 | AG69: 0 | AH69: 0 | AI69: =SUM(C69:AH69) -> 0 | AJ69: =SUM(AI66:AI69) -> 0 | AM69: Retorno acumulado da carteira | AO69: =AO67 -> -1 | AP69: 0 | AQ69: =AQ67 | AS69: =AS67 | AT69: =AT67 | AU69: =AU67 | AV69: =AV67 | AW69: =AW67 | AX69: =AX67
B70: Valor final no mês | C70: 0 | D70: 0 | E70: 0 | F70: 0 | G70: 0 | H70: 0 | I70: 0 | J70: 0 | K70: 0 | L70: 0 | M70: 0 | N70: 0 | O70: 0 | P70: 0 | Q70: 0 | R70: 0 | S70: 0 | T70: 0 | U70: 0 | V70: 0 | W70: 0 | X70: 0 | Y70: 0 | Z70: 0 | AA70: 0 | AB70: 0 | AC70: 0 | AD70: 0 | AE70: 0 | AF70: 0 | AG70: 0 | AH70: 0 | AI70: =SUM(C70:AH70) -> 0 | AJ70: =AJ69-AI70 -> 0
B71: Rentabilidade (ao mês) | C71: =IFERROR(IF(C70=0,(-C68/C66)-1,C72),"") | D71: =IFERROR(IF(D70=0,(-D68/D66)-1,D72),"") | E71: =IFERROR(IF(E70=0,(-E68/E66)-1,E72),"") | F71: =IFERROR(IF(F70=0,(-F68/F66)-1,F72),"") | G71: =IFERROR(IF(G70=0,(-G68/G66)-1,G72),"") | H71: =IFERROR(IF(H70=0,(-H68/H66)-1,H72),"") | I71: =IFERROR(IF(I70=0,(-I68/I66)-1,I72),"") | J71: =IFERROR(IF(J70=0,(-J68/J66)-1,J72),"") | ... AI71: =IFERROR(IF(AI70=0,(-AI68/AI66)-1,AI72),"") | AJ71: =(AI70*AI71) -> 0 | AM71: =AM66 -> 45658 | AN71: =AN66 -> 45689 | AO71: =AO66 -> 45717 | AP71: =AP66 | AQ71: =AQ66 | AR71: =AR66 | AS71: =AS66 | AT71: =AT66 | ... AX71: =AX66
B72: Não mexer | C72: =IFERROR(IF(AND(C66<>0,C70=""),"",(C70/(C66+C67+C68+C69))-1),"") | D72: =IFERROR(IF(AND(D66<>0,D70=""),"",(D70/(D66+D67+D68+D69))-1),"") | E72: =IFERROR(IF(AND(E66<>0,E70=""),"",(E70/(E66+E67+E68+E69))-1),"") | F72: =IFERROR(IF(AND(F66<>0,F70=""),"",(F70/(F66+F67+F68+F69))-1),"") | G72: =IFERROR(IF(AND(G66<>0,G70=""),"",(G70/(G66+G67+G68+G69))-1),"") | H72: =IFERROR(IF(AND(H66<>0,H70=""),"",(H70/(H66+H67+H68+H69))-1),"") | I72: =IFERROR(IF(AND(I66<>0,I70=""),"",(I70/(I66+I67+I68+I69))-1),"") | J72: =IFERROR(IF(AND(J66<>0,J70=""),"",(J70/(J66+J67+J68+J69))-1),"") | ... AI72: =IFERROR(IF(AND(AI66<>0,AI70=""),"",(AI70/(AI66+AI67+AI68+AI69))-1),"")
B73: Ativo/PL | C73: =IFERROR(C70/$AI$70,"") | D73: =IFERROR(D70/$AI$70,"") | E73: =IFERROR(E70/$AI$70,"") | F73: =IFERROR(F70/$AI$70,"") | G73: =IFERROR(G70/$AI$70,"") | H73: =IFERROR(H70/$AI$70,"") | I73: =IFERROR(I70/$AI$70,"") | J73: =IFERROR(J70/$AI$70,"") | ... AI73: =IFERROR(AI70/$AI$70,"") | AJ73: =AI70-AI66 -> 0 | AK73: =AI70/AI66-1 -> #DIV/0! | AM73: =IFERROR(IF(AM67<>0,(1+AL73)*(1+AM67)-1,""),"") -> 0.0082489277 | AN73: =IFERROR(IF(AN67<>0,(1+AM73)*(1+AN67)-1,""),"") -> -0.00073037418 | AO73: =IFERROR(IF(AO67<>0,(1+AN73)*(1+AO67)-1,""),"") -> -1 | AP73: =IFERROR(IF(AP67<>0,(1+AO73)*(1+AP67)-1,""),"") -> -1 | AQ73: =IFERROR(IF(AQ67<>0,(1+AP73)*(1+AQ67)-1,""),"") -> -1 | AR73: =IFERROR(IF(AR67<>0,(1+AQ73)*(1+AR67)-1,""),"") -> -1 | AS73: =IFERROR(IF(AS67<>0,(1+AR73)*(1+AS67)-1,""),"") -> -1 | AT73: =IFERROR(IF(AT67<>0,(1+AS73)*(1+AT67)-1,""),"") -> -1 | ... AX73: =IFERROR(IF(AX67<>0,(1+AW73)*(1+AX67)-1,""),"") -> -1
A74: 45931 | B74: Valor-base | C74: =IF(C78="","",C70) -> 0 | D74: =IF(D78="","",D70) -> 0 | E74: =IF(E78="","",E70) -> 0 | F74: =IF(F78="","",F70) -> 0 | G74: =IF(G78="","",G70) -> 0 | H74: =IF(H78="","",H70) -> 0 | I74: =IF(I78="","",I70) -> 0 | J74: =IF(J78="","",J70) -> 0 | ... AH74: =IF(AH78="","",AH70) -> 0 | AI74: =SUM(C74:AH74) -> 0 | AM74: =AM73 -> 0.0082489277 | AN74: =AN73 -> -0.00073037418 | AO74: 0 | AP74: 0 | AQ74: 0 | AR74: 0 | AS74: 0 | AT74: 0 | AU74: 0 | AV74: 0 | AW74: 0 | AX74: 0
B75: Investimento (+) | C75: 0 | D75: 0 | E75: 0 | F75: 0 | G75: 0 | H75: 0 | I75: 0 | J75: 0 | K75: 0 | L75: 0 | M75: 0 | N75: 0 | O75: 0 | P75: 0 | Q75: 0 | R75: 0 | S75: 0 | T75: 0 | U75: 0 | V75: 0 | W75: 0 | X75: 0 | Y75: 0 | Z75: 0 | AA75: 0 | AB75: 0 | AC75: 0 | AD75: 0 | AE75: 0 | AF75: 0 | AG75: 0 | AH75: 0 | AI75: =SUM(C75:AH75) -> 0
B76: Resgate (-) | C76: 0 | D76: 0 | E76: 0 | F76: 0 | G76: 0 | H76: 0 | I76: 0 | J76: 0 | K76: 0 | L76: 0 | M76: 0 | N76: 0 | O76: 0 | P76: 0 | Q76: 0 | R76: 0 | S76: 0 | T76: 0 | U76: 0 | V76: 0 | W76: 0 | X76: 0 | Y76: 0 | Z76: 0 | AA76: 0 | AB76: 0 | AC76: 0 | AD76: 0 | AE76: 0 | AF76: 0 | AG76: 0 | AH76: 0 | AI76: =SUM(C76:AH76) -> 0
B77: Rebecimento de proventos (-) | C77: 0 | D77: 0 | E77: 0 | F77: 0 | G77: 0 | H77: 0 | I77: 0 | J77: 0 | K77: 0 | L77: 0 | M77: 0 | N77: 0 | O77: 0 | P77: 0 | Q77: 0 | R77: 0 | S77: 0 | T77: 0 | U77: 0 | V77: 0 | W77: 0 | X77: 0 | Y77: 0 | Z77: 0 | AA77: 0 | AB77: 0 | AC77: 0 | AD77: 0 | AE77: 0 | AF77: 0 | AG77: 0 | AH77: 0 | AI77: =SUM(C77:AH77) -> 0 | AJ77: =SUM(AI74:AI77) -> 0
B78: Valor final no mês | C78: 0 | D78: 0 | E78: 0 | F78: 0 | G78: 0 | H78: 0 | I78: 0 | J78: 0 | K78: 0 | L78: 0 | M78: 0 | N78: 0 | O78: 0 | P78: 0 | Q78: 0 | R78: 0 | S78: 0 | T78: 0 | U78: 0 | V78: 0 | W78: 0 | X78: 0 | Y78: 0 | Z78: 0 | AA78: 0 | AB78: 0 | AC78: 0 | AD78: 0 | AE78: 0 | AF78: 0 | AG78: 0 | AH78: 0 | AI78: =SUM(C78:AH78) -> 0 | AJ78: =+AJ77-AI78 -> 0
B79: Rentabilidade (ao mês) | C79: =IFERROR(IF(C78=0,(-C76/C74)-1,C80),"") | D79: =IFERROR(IF(D78=0,(-D76/D74)-1,D80),"") | E79: =IFERROR(IF(E78=0,(-E76/E74)-1,E80),"") | F79: =IFERROR(IF(F78=0,(-F76/F74)-1,F80),"") | G79: =IFERROR(IF(G78=0,(-G76/G74)-1,G80),"") | H79: =IFERROR(IF(H78=0,(-H76/H74)-1,H80),"") | I79: =IFERROR(IF(I78=0,(-I76/I74)-1,I80),"") | J79: =IFERROR(IF(J78=0,(-J76/J74)-1,J80),"") | ... AI79: =IFERROR(IF(AI78=0,(-AI76/AI74)-1,AI80),"") | AJ79: =AI78*AI79 -> 0
B80: Não mexer | C80: =IFERROR(IF(AND(C74<>0,C78=""),"",(C78/(C74+C75+C76+C77))-1),"") | D80: =IFERROR(IF(AND(D74<>0,D78=""),"",(D78/(D74+D75+D76+D77))-1),"") | E80: =IFERROR(IF(AND(E74<>0,E78=""),"",(E78/(E74+E75+E76+E77))-1),"") | F80: =IFERROR(IF(AND(F74<>0,F78=""),"",(F78/(F74+F75+F76+F77))-1),"") | G80: =IFERROR(IF(AND(G74<>0,G78=""),"",(G78/(G74+G75+G76+G77))-1),"") | H80: =IFERROR(IF(AND(H74<>0,H78=""),"",(H78/(H74+H75+H76+H77))-1),"") | I80: =IFERROR(IF(AND(I74<>0,I78=""),"",(I78/(I74+I75+I76+I77))-1),"") | J80: =IFERROR(IF(AND(J74<>0,J78=""),"",(J78/(J74+J75+J76+J77))-1),"") | ... AI80: =IFERROR(IF(AND(AI74<>0,AI78=""),"",(AI78/(AI74+AI75+AI76+AI77))-1),"")
B81: Ativo/PL | C81: =IFERROR(C78/$AI$78,"") | D81: =IFERROR(D78/$AI$78,"") | E81: =IFERROR(E78/$AI$78,"") | F81: =IFERROR(F78/$AI$78,"") | G81: =IFERROR(G78/$AI$78,"") | H81: =IFERROR(H78/$AI$78,"") | I81: =IFERROR(I78/$AI$78,"") | J81: =IFERROR(J78/$AI$78,"") | ... AI81: =IFERROR(AI78/$AI$78,"") | AJ81: =AI78-AI74 -> 0 | AK81: =AI78/AI74-1 -> #DIV/0!
A82: 45962 | B82: Valor-base | C82: =IF(C86="","",C78) -> 0 | D82: =IF(D86="","",D78) -> 0 | E82: =IF(E86="","",E78) -> 0 | F82: =IF(F86="","",F78) -> 0 | G82: =IF(G86="","",G78) -> 0 | H82: =IF(H86="","",H78) -> 0 | I82: =IF(I86="","",I78) -> 0 | J82: =IF(J86="","",J78) -> 0 | ... AH82: =IF(AH86="","",AH78) -> 0 | AI82: =SUM(C82:AH82) -> 0
B83: Investimento (+) | C83: 0 | D83: 0 | E83: 0 | F83: 0 | G83: 0 | H83: 0 | I83: 0 | J83: 0 | K83: 0 | L83: 0 | M83: 0 | N83: 0 | O83: 0 | P83: 0 | Q83: 0 | R83: 0 | S83: 0 | T83: 0 | U83: 0 | V83: 0 | W83: 0 | X83: 0 | Y83: 0 | Z83: 0 | AA83: 0 | AB83: 0 | AC83: 0 | AD83: 0 | AE83: 0 | AF83: 0 | AG83: 0 | AH83: 0 | AI83: =SUM(C83:AH83) -> 0
B84: Resgate (-) | C84: 0 | D84: 0 | E84: 0 | F84: 0 | G84: 0 | H84: 0 | I84: 0 | J84: 0 | K84: 0 | L84: 0 | M84: 0 | N84: 0 | O84: 0 | P84: 0 | Q84: 0 | R84: 0 | S84: 0 | T84: 0 | U84: 0 | V84: 0 | W84: 0 | X84: 0 | Y84: 0 | Z84: 0 | AA84: 0 | AB84: 0 | AC84: 0 | AD84: 0 | AE84: 0 | AF84: 0 | AG84: 0 | AH84: 0 | AI84: =SUM(C84:AH84) -> 0
B85: Rebecimento de proventos (-) | C85: 0 | D85: 0 | E85: 0 | F85: 0 | G85: 0 | H85: 0 | I85: 0 | J85: 0 | K85: 0 | L85: 0 | M85: 0 | N85: 0 | O85: 0 | P85: 0 | Q85: 0 | R85: 0 | S85: 0 | T85: 0 | U85: 0 | V85: 0 | W85: 0 | X85: 0 | Y85: 0 | Z85: 0 | AA85: 0 | AB85: 0 | AC85: 0 | AD85: 0 | AE85: 0 | AF85: 0 | AG85: 0 | AH85: 0 | AI85: =SUM(C85:AH85) -> 0 | AJ85: =SUM(AI82:AI85) -> 0
B86: Valor final no mês | C86: 0 | D86: 0 | E86: 0 | F86: 0 | G86: 0 | H86: 0 | I86: 0 | J86: 0 | K86: 0 | L86: 0 | M86: 0 | N86: 0 | O86: 0 | P86: 0 | Q86: 0 | R86: 0 | S86: 0 | T86: 0 | U86: 0 | V86: 0 | W86: 0 | X86: 0 | Y86: 0 | Z86: 0 | AA86: 0 | AB86: 0 | AC86: 0 | AD86: 0 | AE86: 0 | AF86: 0 | AG86: 0 | AH86: 0 | AI86: =SUM(C86:AH86) -> 0 | AJ86: =AJ85-AI86 -> 0
B87: Rentabilidade (ao mês) | C87: =IFERROR(IF(C86=0,(-C84/C82)-1,C88),"") | D87: =IFERROR(IF(D86=0,(-D84/D82)-1,D88),"") | E87: =IFERROR(IF(E86=0,(-E84/E82)-1,E88),"") | F87: =IFERROR(IF(F86=0,(-F84/F82)-1,F88),"") | G87: =IFERROR(IF(G86=0,(-G84/G82)-1,G88),"") | H87: =IFERROR(IF(H86=0,(-H84/H82)-1,H88),"") | I87: =IFERROR(IF(I86=0,(-I84/I82)-1,I88),"") | J87: =IFERROR(IF(J86=0,(-J84/J82)-1,J88),"") | ... AI87: =IFERROR(IF(AI86=0,(-AI84/AI82)-1,AI88),"") | AJ87: =AI86*AI87 -> 0
B88: Não mexer | C88: =IFERROR(IF(AND(C82<>0,C86=""),"",(C86/(C82+C83+C84+C85))-1),"") | D88: =IFERROR(IF(AND(D82<>0,D86=""),"",(D86/(D82+D83+D84+D85))-1),"") | E88: =IFERROR(IF(AND(E82<>0,E86=""),"",(E86/(E82+E83+E84+E85))-1),"") | F88: =IFERROR(IF(AND(F82<>0,F86=""),"",(F86/(F82+F83+F84+F85))-1),"") | G88: =IFERROR(IF(AND(G82<>0,G86=""),"",(G86/(G82+G83+G84+G85))-1),"") | H88: =IFERROR(IF(AND(H82<>0,H86=""),"",(H86/(H82+H83+H84+H85))-1),"") | I88: =IFERROR(IF(AND(I82<>0,I86=""),"",(I86/(I82+I83+I84+I85))-1),"") | J88: =IFERROR(IF(AND(J82<>0,J86=""),"",(J86/(J82+J83+J84+J85))-1),"") | ... AI88: =IFERROR(IF(AND(AI82<>0,AI86=""),"",(AI86/(AI82+AI83+AI84+AI85))-1),"")
B89: Ativo/PL | C89: =IFERROR(C86/$AI$86,"") | D89: =IFERROR(D86/$AI$86,"") | E89: =IFERROR(E86/$AI$86,"") | F89: =IFERROR(F86/$AI$86,"") | G89: =IFERROR(G86/$AI$86,"") | H89: =IFERROR(H86/$AI$86,"") | I89: =IFERROR(I86/$AI$86,"") | J89: =IFERROR(J86/$AI$86,"") | ... AI89: =IFERROR(AI86/$AI$86,"") | AJ89: =AI86-AI82 -> 0 | AK89: =AI86/AI82-1 -> #DIV/0!
A90: 45992 | B90: Valor-base | C90: =IF(C94="","",C86) -> 0 | D90: =IF(D86="","",D86) -> 0 | E90: =IF(E86="","",E86) -> 0 | F90: =IF(F86="","",F86) -> 0 | G90: =IF(G86="","",G86) -> 0 | H90: =IF(H86="","",H86) -> 0 | I90: =IF(I86="","",I86) -> 0 | J90: =IF(J86="","",J86) -> 0 | K90: =IF(K86="","",K86) -> 0 | ... AH90: =IF(AH86="","",AH86) -> 0 | AI90: =SUM(C90:AH90) -> 0
B91: Investimento (+) | C91: 0 | D91: 0 | E91: 0 | F91: 0 | G91: 0 | H91: 0 | I91: 0 | J91: 0 | K91: 0 | L91: 0 | M91: 0 | N91: 0 | O91: 0 | P91: 0 | Q91: 0 | R91: 0 | S91: 0 | T91: 0 | U91: 0 | V91: 0 | W91: 0 | X91: 0 | Y91: 0 | Z91: 0 | AA91: 0 | AB91: 0 | AC91: 0 | AD91: 0 | AE91: 0 | AF91: 0 | AG91: 0 | AH91: 0 | AI91: =SUM(C91:AH91) -> 0
B92: Resgate (-) | C92: 0 | D92: 0 | E92: 0 | F92: 0 | G92: 0 | H92: 0 | I92: 0 | J92: 0 | K92: 0 | L92: 0 | M92: 0 | N92: 0 | O92: 0 | P92: 0 | Q92: 0 | R92: 0 | S92: 0 | T92: 0 | U92: 0 | V92: 0 | W92: 0 | X92: 0 | Y92: 0 | Z92: 0 | AA92: 0 | AB92: 0 | AC92: 0 | AD92: 0 | AE92: 0 | AF92: 0 | AG92: 0 | AH92: 0 | AI92: =SUM(C92:AH92) -> 0
B93: Rebecimento de proventos (-) | C93: 0 | D93: 0 | E93: 0 | F93: 0 | G93: 0 | H93: 0 | I93: 0 | J93: 0 | K93: 0 | L93: 0 | M93: 0 | N93: 0 | O93: 0 | P93: 0 | Q93: 0 | R93: 0 | S93: 0 | T93: 0 | U93: 0 | V93: 0 | W93: 0 | X93: 0 | Y93: 0 | Z93: 0 | AA93: 0 | AB93: 0 | AC93: 0 | AD93: 0 | AE93: 0 | AF93: 0 | AG93: 0 | AH93: 0 | AI93: =SUM(C93:AH93) -> 0 | AJ93: =SUM(AI90:AI93) -> 0
B94: Valor final no mês | C94: 0 | D94: 0 | E94: 0 | F94: 0 | G94: 0 | H94: 0 | I94: 0 | J94: 0 | K94: 0 | L94: 0 | M94: 0 | N94: 0 | O94: 0 | P94: 0 | Q94: 0 | R94: 0 | S94: 0 | T94: 0 | U94: 0 | V94: 0 | W94: 0 | X94: 0 | Y94: 0 | Z94: 0 | AA94: 0 | AB94: 0 | AC94: 0 | AD94: 0 | AE94: 0 | AF94: 0 | AG94: 0 | AH94: 0 | AI94: =SUM(C94:AH94) -> 0 | AJ94: =AJ93-AI94 -> 0
B95: Rentabilidade (ao mês) | C95: =IFERROR(IF(C94=0,(-C92/C90)-1,C96),"") | D95: =IFERROR(IF(D94=0,(-D92/D90)-1,D96),"") | E95: =IFERROR(IF(E94=0,(-E92/E90)-1,E96),"") | F95: =IFERROR(IF(F94=0,(-F92/F90)-1,F96),"") | G95: =IFERROR(IF(G94=0,(-G92/G90)-1,G96),"") | H95: =IFERROR(IF(H94=0,(-H92/H90)-1,H96),"") | I95: =IFERROR(IF(I94=0,(-I92/I90)-1,I96),"") | J95: =IFERROR(IF(J94=0,(-J92/J90)-1,J96),"") | ... AI95: =IFERROR(IF(AI94=0,(-AI92/AI90)-1,AI96),"") | AJ95: =AI94*AI95 -> 0
B96: Não mexer | C96: =IFERROR(IF(AND(C90<>0,C94=""),"",(C94/(C90+C91+C92+C93))-1),"") | D96: =IFERROR(IF(AND(D90<>0,D94=""),"",(D94/(D90+D91+D92+D93))-1),"") | E96: =IFERROR(IF(AND(E90<>0,E94=""),"",(E94/(E90+E91+E92+E93))-1),"") | F96: =IFERROR(IF(AND(F90<>0,F94=""),"",(F94/(F90+F91+F92+F93))-1),"") | G96: =IFERROR(IF(AND(G90<>0,G94=""),"",(G94/(G90+G91+G92+G93))-1),"") | H96: =IFERROR(IF(AND(H90<>0,H94=""),"",(H94/(H90+H91+H92+H93))-1),"") | I96: =IFERROR(IF(AND(I90<>0,I94=""),"",(I94/(I90+I91+I92+I93))-1),"") | J96: =IFERROR(IF(AND(J90<>0,J94=""),"",(J94/(J90+J91+J92+J93))-1),"") | ... AI96: =IFERROR(IF(AND(AI90<>0,AI94=""),"",(AI94/(AI90+AI91+AI92+AI93))-1),"")
B97: Ativo/PL | C97: =IFERROR(C94/$AI$94,"") | D97: =IFERROR(D94/$AI$94,"") | E97: =IFERROR(E94/$AI$94,"") | F97: =IFERROR(F94/$AI$94,"") | G97: =IFERROR(G94/$AI$94,"") | H97: =IFERROR(H94/$AI$94,"") | I97: =IFERROR(I94/$AI$94,"") | J97: =IFERROR(J94/$AI$94,"") | ... AI97: =IFERROR(AI94/$AI$94,"") | AJ97: =AI94-AI90 -> 0 | AK97: =AI94/AI90-1 -> #DIV/0!
AA98: =AA96
B100: Descrição | C100: =IF(C101="","",C1) -> Tesouro Alexa | D100: =IF(D101="","",D1) -> Tesouro Nasser | E100: =IF(E101="","",E1) -> #REF! | F100: =IF(F101="","",F1) -> LFTS11 BTG ALEXA | G100: =IF(G101="","",G1) -> FUNDO BTG DIGITAL SELIC FIRF | H100: =IF(H101="","",H1) -> CDB NU NASSER | I100: =IF(I101="","",I1) -> BB FUNDO-RF LP HIGH | J100: =IF(J101="","",J1) -> FUNDO BTG CDB PLUS FIRF CRPR | ... AH100: =IF(AH101="","",AH1) | AI100: Patrimônio
B101: Ativo/PL do último mês preenchido | C101: =IF(IF(C97="",IF(C89="",IF(C81="",IF(C73="",IF(C65="",IF(C57="",IF(C49="",IF(C41="",IF(C33="",IF(C25="",IF(C17="",C9,C17),C25),C33),C41),C49),C57),C65),C73),C81),C89),C97)=0,"",IF(C97="",IF(C89="",IF(C81="",IF(C73="",IF(C65="",IF(C57="",IF(C49="",IF(C41="",IF(C33="",IF(C25="",IF(C17="",C9,C17),C25),C33),C41),C49),C57),C65),C73),C81),C89),C97)) -> 0.010151186 | D101: =IF(IF(D97="",IF(D89="",IF(D81="",IF(D73="",IF(D65="",IF(D57="",IF(D49="",IF(D41="",IF(D33="",IF(D25="",IF(D17="",D9,D17),D25),D33),D41),D49),D57),D65),D73),D81),D89),D97)=0,"",IF(D97="",IF(D89="",IF(D81="",IF(D73="",IF(D65="",IF(D57="",IF(D49="",IF(D41="",IF(D33="",IF(D25="",IF(D17="",D9,D17),D25),D33),D41),D49),D57),D65),D73),D81),D89),D97)) -> 0.045594367 | E101: =IF(IF(E97="",IF(E89="",IF(E81="",IF(E73="",IF(E65="",IF(E57="",IF(E49="",IF(E41="",IF(#REF!="",IF(E25="",IF(E17="",E9,E17),E25),#REF!),E41),E49),E57),E65),E73),E81),E89),E97)=0,"",IF(E97="",IF(E89="",IF(E81="",IF(E73="",IF(E65="",IF(E57="",IF(E49="",IF(E41="",IF(#REF!="",IF(E25="",IF(E17="",E9,E17),E25),#REF!),E41),E49),E57),E65),E73),E81),E89),E97)) -> #REF! | F101: =IF(IF(F97="",IF(F89="",IF(F81="",IF(F73="",IF(F65="",IF(F57="",IF(F49="",IF(F41="",IF(F33="",IF(F25="",IF(F17="",F9,F17),F25),F33),F41),F49),F57),F65),F73),F81),F89),F97)=0,"",IF(F97="",IF(F89="",IF(F81="",IF(F73="",IF(F65="",IF(F57="",IF(F49="",IF(F41="",IF(F33="",IF(F25="",IF(F17="",F9,F17),F25),F33),F41),F49),F57),F65),F73),F81),F89),F97)) -> 0.030727177 | G101: =IF(IF(G97="",IF(G89="",IF(G81="",IF(G73="",IF(G65="",IF(G57="",IF(G49="",IF(G41="",IF(G33="",IF(G25="",IF(G17="",G9,G17),G25),G33),G41),G49),G57),G65),G73),G81),G89),G97)=0,"",IF(G97="",IF(G89="",IF(G81="",IF(G73="",IF(G65="",IF(G57="",IF(G49="",IF(G41="",IF(G33="",IF(G25="",IF(G17="",G9,G17),G25),G33),G41),G49),G57),G65),G73),G81),G89),G97)) -> 0.034541355 | H101: =IF(IF(H97="",IF(H89="",IF(H81="",IF(H73="",IF(H65="",IF(H57="",IF(H49="",IF(H41="",IF(H33="",IF(H25="",IF(H17="",H9,H17),H25),H33),H41),H49),H57),H65),H73),H81),H89),H97)=0,"",IF(H97="",IF(H89="",IF(H81="",IF(H73="",IF(H65="",IF(H57="",IF(H49="",IF(H41="",IF(H33="",IF(H25="",IF(H17="",H9,H17),H25),H33),H41),H49),H57),H65),H73),H81),H89),H97)) -> 0.004647413 | I101: =IF(IF(I97="",IF(I89="",IF(I81="",IF(I73="",IF(I65="",IF(I57="",IF(I49="",IF(I41="",IF(I33="",IF(I25="",IF(I17="",I9,I17),I25),I33),I41),I49),I57),I65),I73),I81),I89),I97)=0,"",IF(I97="",IF(I89="",IF(I81="",IF(I73="",IF(I65="",IF(I57="",IF(I49="",IF(I41="",IF(I33="",IF(I25="",IF(I17="",I9,I17),I25),I33),I41),I49),I57),I65),I73),I81),I89),I97)) -> 0.056796877 | J101: =IF(IF(J97="",IF(J89="",IF(J81="",IF(J73="",IF(J65="",IF(J57="",IF(J49="",IF(J41="",IF(J33="",IF(J25="",IF(J17="",J9,J17),J25),J33),J41),J49),J57),J65),J73),J81),J89),J97)=0,"",IF(J97="",IF(J89="",IF(J81="",IF(J73="",IF(J65="",IF(J57="",IF(J49="",IF(J41="",IF(J33="",IF(J25="",IF(J17="",J9,J17),J25),J33),J41),J49),J57),J65),J73),J81),J89),J97)) -> 0.070166622 | K101: =IF(IF(K97="",IF(K89="",IF(K81="",IF(K73="",IF(K65="",IF(K57="",IF(K49="",IF(K41="",IF(K33="",IF(K25="",IF(K17="",K9,K17),K25),K33),K41),K49),K57),K65),K73),K81),K89),K97)=0,"",IF(K97="",IF(K89="",IF(K81="",IF(K73="",IF(K65="",IF(K57="",IF(K49="",IF(K41="",IF(K33="",IF(K25="",IF(K17="",K9,K17),K25),K33),K41),K49),K57),K65),K73),K81),K89),K97)) -> 0.068663935 | L101: =IF(IF(L97="",IF(L89="",IF(L81="",IF(L73="",IF(L65="",IF(L57="",IF(L49="",IF(L41="",IF(L33="",IF(L25="",IF(L17="",L9,L17),L25),L33),L41),L49),L57),L65),L73),L81),L89),L97)=0,"",IF(L97="",IF(L89="",IF(L81="",IF(L73="",IF(L65="",IF(L57="",IF(L49="",IF(L41="",IF(L33="",IF(L25="",IF(L17="",L9,L17),L25),L33),L41),L49),L57),L65),L73),L81),L89),L97)) -> 0.029296972 | M101: =IF(IF(M97="",IF(M89="",IF(M81="",IF(M73="",IF(M65="",IF(M57="",IF(M49="",IF(M41="",IF(M33="",IF(M25="",IF(M17="",M9,M17),M25),M33),M41),M49),M57),M65),M73),M81),M89),M97)=0,"",IF(M97="",IF(M89="",IF(M81="",IF(M73="",IF(M65="",IF(M57="",IF(M49="",IF(M41="",IF(M33="",IF(M25="",IF(M17="",M9,M17),M25),M33),M41),M49),M57),M65),M73),M81),M89),M97)) -> 0.11577309 | ... AI101: =IF(IF(AI97="",IF(AI89="",IF(AI81="",IF(AI73="",IF(AI65="",IF(AI57="",IF(AI49="",IF(AI41="",IF(AI33="",IF(AI25="",IF(AI17="",AI9,AI17),AI25),AI33),AI41),AI49),AI57),AI65),AI73),AI81),AI89),AI97)=0,"",IF(AI97="",IF(AI89="",IF(AI81="",IF(AI73="",IF(AI65="",IF(AI57="",IF(AI49="",IF(AI41="",IF(AI33="",IF(AI25="",IF(AI17="",AI9,AI17),AI25),AI33),AI41),AI49),AI57),AI65),AI73),AI81),AI89),AI97)) -> 1

Sheet % de Alocação da Carteira 02_25
B2: ANALISE % de Alocação da Carteira "Nasser Family"p/ Produto Financeiro (02/2024) | M2: ALOCAÇÃO % COMPACTA
E3: =+SUM(E4:E14) -> 1
B4: CAIXA | D4: =+'Planilha de Rentabilidade'!E14 -> -70858 | E4: =D4/$E$15 -> -0.020999058 | L4: IPCA + | M4: =SUM(D5:D7) -> 419476.55 | N4: =M4/$M$15 -> 0.12431359
B5: TESOURO IPCA+2035 | D5: =+'Planilha de Rentabilidade'!Q14 -> 63978.03 | E5: =D5/$E$15 -> 0.018960151 | M5: 0 | N5: =M5/$M$15 -> 0
B6: DEBENTURE | D6: =+'Planilha de Rentabilidade'!P14 -> 232984.34 | E6: =D6/$E$15 -> 0.069045862 | M6: 0 | N6: =M6/$M$15 -> 0
B7: CRI CRA | D7: ='Planilha de Rentabilidade'!O14 -> 122514.18 | E7: =D7/$E$15 -> 0.036307578 | L7: LCA | M7: =+D11 -> 0 | N7: =M7/$M$15 -> 0
B8: TESOURO SELIC + LFTS11 | D8: =+'Planilha de Rentabilidade'!C14+'Planilha de Rentabilidade'!D14+'Planilha de Rentabilidade'!F14+'Planilha de Rentabilidade'!S14 -> 312525.35 | E8: =D8/$E$15 -> 0.092618165 | L8: RENDA FIXA | M8: =D8+D12+D13 -> 1104875.5 | N8: =M8/$M$15 -> 0.32743437
B9: MOEDAS | D9: ='Planilha de Rentabilidade'!L14 -> 98858 | E9: =D9/$E$15 -> 0.029296972 | L9: GOLD + $$ | M9: =+D10 -> 390657.99 | N9: =M9/$M$15 -> 0.11577309
B10: GOLD+$ | D10: ='Planilha de Rentabilidade'!M14 -> 390657.99 | E10: =D10/$E$15 -> 0.11577309 | L10: MOEDAS | M10: =D9 -> 98858 | N10: =M10/$M$15 -> 0.029296972
B11: LCA | D11: =0 -> 0 | E11: =D11/$E$15 -> 0 | N11: =M11/$M$15 -> 0
B12: FUNDO DI | D12: ='Planilha de Rentabilidade'!G14+'Planilha de Rentabilidade'!I14+'Planilha de Rentabilidade'!J14 -> 544972.59 | E12: =D12/$E$15 -> 0.16150486 | L12: CAIXA | M12: =+D4 -> -70858 | N12: =M12/$M$15 -> -0.020999058
B13: CDB DI | D13: =+'Planilha de Rentabilidade'!H14+'Planilha de Rentabilidade'!K14 -> 247377.55 | E13: =D13/$E$15 -> 0.073311348 | N13: =M13/$M$15 -> 0
B14: RENDA VARIAVEL | D14: =B33 -> 1431331.8 | E14: =D14/$E$15 -> 0.42418103 | L14: R.V. | M14: =D14 -> 1431331.8 | N14: =M14/$M$15 -> 0.42418103
C15: Total da Carteira Nasser Family ==> | E15: =SUM(D4:D14) -> 3374341.8 | M15: =SUM(M4:M14) -> 3374341.8 | N15: =SUM(N4:N14) -> 1
B18: ANALISE % Alocação da Carteira "Nasser Family" RENDA VARIAVEL(02/2024)
C19: % Renda Variavel Alocadas por Setor
B20: ='Planilha de Rentabilidade'!Z14+'Planilha de Rentabilidade'!AA14+'Planilha de Rentabilidade'!W14 -> 0 | C20: =B20/$B$33 -> 0 | D20: IRON ORE
B21: =0 -> 0 | C21: =B21/$B$33 -> 0 | D21: SOJA
B22: ='Planilha de Rentabilidade'!U14+'Planilha de Rentabilidade'!AF14 -> 936746.16 | C22: =B22/$B$33 -> 0.65445772 | D22: Electric Vehicle
B23: ='Planilha de Rentabilidade'!AD14+'Planilha de Rentabilidade'!V14 -> 192245 | C23: =B23/$B$33 -> 0.13431197 | D23: MELI
B24: ='Planilha de Rentabilidade'!AH14 -> 0 | C24: =B24/$B$33 -> 0 | D24: LITHIUM
B25: 0 | C25: =B25/$B$33 -> 0 | D25: ENERGIA
B26: 0 | C26: =B26/$B$33 -> 0 | D26: CELULOSE
B27: 0 | C27: =B27/$B$33 -> 0 | D27: Saude
B28: =+'Planilha de Rentabilidade'!R14 -> 73020 | C28: =B28/$B$33 -> 0.051015425 | D28: AURA
B29: =+'Planilha de Rentabilidade'!X14+'Planilha de Rentabilidade'!AC14 -> 200168.15 | C29: =B29/$B$33 -> 0.13984748 | D29: AMD
B30: ='Planilha de Rentabilidade'!AB79+'Planilha de Rentabilidade'!AC79 -> 0 | C30: =B30/$B$33 -> 0 | D30: APPLE
B31: =+'Planilha de Rentabilidade'!N14 -> 29152.5 | C31: =B31/$B$33 -> 0.020367395 | D31: INTEL
B32: =+'Planilha de Rentabilidade'!AB14 -> 0 | C32: =B32/$B$33 -> 0 | D32: WEGE
B33: =SUM(B20:B32) -> 1431331.8 | C33: =B33/$B$33 -> 1

Sheet Alocação da Carteira 04_25
B2: ANALISE % de Alocação da Carteira "Nasser Family"p/ Produto Financeiro (04/2024) | M2: ALOCAÇÃO % COMPACTA
E3: =+SUM(E4:E14) -> #DIV/0!
B4: CAIXA | D4: =+'Planilha de Rentabilidade'!E30 -> 0 | E4: =D4/$E$15 -> #DIV/0! | L4: IPCA + | M4: =SUM(D5:D7) -> 0 | N4: =M4/$M$15 -> #DIV/0!
B5: TESOURO IPCA+2029 | D5: =+'Planilha de Rentabilidade'!Q30 -> 0 | E5: =D5/$E$15 -> #DIV/0! | M5: 0 | N5: =M5/$M$15 -> #DIV/0!
B6: DEBENTURE IPCA+7,60% | D6: =+'Planilha de Rentabilidade'!P30 -> 0 | E6: =D6/$E$15 -> #DIV/0! | M6: 0 | N6: =M6/$M$15 -> #DIV/0!
B7: CRI CRA | D7: 0 | E7: =D7/$E$15 -> #DIV/0! | L7: LCA | M7: =+D11 -> 0 | N7: =M7/$M$15 -> #DIV/0!
B8: TESOURO SELIC + LFTS11 | D8: =+'Planilha de Rentabilidade'!C30+'Planilha de Rentabilidade'!D30+'Planilha de Rentabilidade'!F30 -> 0 | E8: =D8/$E$15 -> #DIV/0! | L8: RENDA FIXA | M8: =D8+D12+D13 -> 0 | N8: =M8/$M$15 -> #DIV/0!
B9: MOEDAS | D9: ='Planilha de Rentabilidade'!L30 -> 0 | E9: =D9/$E$15 -> #DIV/0! | L9: $$ | M9: =+D10+D9 -> 0 | N9: =M9/$M$15 -> #DIV/0!
B10: GOLD + $$$ | D10: ='Planilha de Rentabilidade'!M30 -> 0 | E10: =D10/$E$15 -> #DIV/0! | N10: =M10/$M$15 -> #DIV/0!
B11: LCA | D11: =+0 -> 0 | E11: =D11/$E$15 -> #DIV/0! | N11: =M11/$M$15 -> #DIV/0!
B12: FUNDO DI | D12: =+'Planilha de Rentabilidade'!G30+'Planilha de Rentabilidade'!I30 -> 0 | E12: =D12/$E$15 -> #DIV/0! | L12: CAIXA | M12: =+D4 -> 0 | N12: =M12/$M$15 -> #DIV/0!
B13: CDB DI | D13: =+'Planilha de Rentabilidade'!H30+'Planilha de Rentabilidade'!J30+'Planilha de Rentabilidade'!K30+'Planilha de Rentabilidade'!S30+'Planilha de Rentabilidade'!V30 -> 0 | E13: =D13/$E$15 -> #DIV/0! | N13: =M13/$M$15 -> #DIV/0!
B14: RENDA VARIAVEL | D14: =B35 -> 0 | E14: =D14/$E$15 -> #DIV/0! | L14: R.V. | M14: =D14 -> 0 | N14: =M14/$M$15 -> #DIV/0!
E15: =SUM(D4:D14) -> 0 | M15: =SUM(M4:M14) -> 0 | N15: =SUM(N4:N14) -> #DIV/0!
B18: ANALISE % Alocação da Carteira "Nasser Family" RENDA VARIAVEL(04/2024)
C19: % Renda Variavel Alocadas por Setor
B20: =+'Planilha de Rentabilidade'!Z30 -> 0 | C20: =B20/$B$35 -> #DIV/0! | D20: IRON ORE
B21: =+'Planilha de Rentabilidade'!O30 -> 0 | C21: =B21/$B$35 -> #DIV/0! | D21: SOJA
B22: =+'Planilha de Rentabilidade'!U30+'Planilha de Rentabilidade'!AB30 -> 0 | C22: =B22/$B$35 -> #DIV/0! | D22: Electric Vehicle
B23: 0 | C23: =B23/$B$35 -> #DIV/0! | D23: Tec.NVIDIA
B24: 0 | C24: =B24/$B$35 -> #DIV/0! | D24: LITHIUM
B25: 0 | C25: =B25/$B$35 -> #DIV/0! | D25: industria BEBIDAS
B26: 0 | C26: =B26/$B$35 -> #DIV/0! | D26: CELULOSE
B27: =+'Planilha de Rentabilidade'!AA30+'Planilha de Rentabilidade'!AC30 -> 0 | C27: =B27/$B$35 -> #DIV/0! | D27: Saude
B28: 0 | C28: =B28/$B$35 -> #DIV/0! | D28: Comodites_GOLD
B29: =+'Planilha de Rentabilidade'!X30+'Planilha de Rentabilidade'!Y30 -> 0 | C29: =B29/$B$35 -> #DIV/0! | D29: ASML
B30: =+'Planilha de Rentabilidade'!T30 -> 0 | C30: =B30/$B$35 -> #DIV/0! | D30: APPLE
B31: =+'Planilha de Rentabilidade'!N30+'Planilha de Rentabilidade'!AH30 -> 0 | C31: =B31/$B$35 -> #DIV/0! | D31: INTEL
B32: 0 | C32: 0 | D32: CARROCERIAS ONIBUS
C33: =SUM(C20:C32) -> #DIV/0!
B35: =SUM(B20:B34) -> 0 | C35: =B35/$B$35 -> #DIV/0!

Sheet % de Alocação da Carteira 03_25
B2: ANALISE % de Alocação da Carteira "Nasser Family"p/ Produto Financeiro (03/2024) | M2: ALOCAÇÃO % COMPACTA
E3: =+SUM(E4:E14) -> #DIV/0!
B4: CAIXA | D4: =+'Planilha de Rentabilidade'!E22 -> 0 | E4: =D4/$E$15 -> #DIV/0! | L4: IPCA + | M4: =SUM(D5:D7) -> 0 | N4: =M4/$M$15 -> #DIV/0!
B5: TESOURO IPCA+2029 | D5: =+'Planilha de Rentabilidade'!Q22 -> 0 | E5: =D5/$E$15 -> #DIV/0! | M5: 0 | N5: =M5/$M$15 -> #DIV/0!
B6: DEBENTURE IPCA+7,60% | D6: =+'Planilha de Rentabilidade'!P22 -> 0 | E6: =D6/$E$15 -> #DIV/0! | M6: 0 | N6: =M6/$M$15 -> #DIV/0!
B7: CRI CRA | D7: 0 | E7: =D7/$E$15 -> #DIV/0! | L7: LCA | M7: =+D11 -> 0 | N7: =M7/$M$15 -> #DIV/0!
B8: TESOURO SELIC + LFTS11 | D8: ='Planilha de Rentabilidade'!C22+'Planilha de Rentabilidade'!D22+'Planilha de Rentabilidade'!F22 -> 0 | E8: =D8/$E$15 -> #DIV/0! | L8: RENDA FIXA | M8: =D8+D12+D13 -> 0 | N8: =M8/$M$15 -> #DIV/0!
B9: MOEDAS | D9: ='Planilha de Rentabilidade'!L22 -> 0 | E9: =D9/$E$15 -> #DIV/0! | L9: GOLD + $$ | M9: =+D10 -> 0 | N9: =M9/$M$15 -> #DIV/0!
B10: GOLD + $$$ | D10: ='Planilha de Rentabilidade'!M22 -> 0 | E10: =D10/$E$15 -> #DIV/0! | L10: MOEDAS | M10: =D9 -> 0 | N10: =M10/$M$15 -> #DIV/0!
B11: LCA | D11: 0 | E11: =D11/$E$15 -> #DIV/0! | N11: =M11/$M$15 -> #DIV/0!
B12: FUNDO DI | D12: ='Planilha de Rentabilidade'!I22+'Planilha de Rentabilidade'!G22 -> 0 | E12: =D12/$E$15 -> #DIV/0! | L12: CAIXA | M12: =+D4 -> 0 | N12: =M12/$M$15 -> #DIV/0!
B13: CDB DI | D13: =+'Planilha de Rentabilidade'!H22+'Planilha de Rentabilidade'!K22+'Planilha de Rentabilidade'!S22+'Planilha de Rentabilidade'!V22+'Planilha de Rentabilidade'!J22 -> 0 | E13: =D13/$E$15 -> #DIV/0! | N13: =M13/$M$15 -> #DIV/0!
B14: RENDA VARIAVEL | D14: =B35 -> 0 | E14: =D14/$E$15 -> #DIV/0! | L14: R.V. | M14: =D14 -> 0 | N14: =M14/$M$15 -> #DIV/0!
C15: Total da Carteira Nasser Family ==> | E15: =SUM(D4:D14) -> 0 | M15: =SUM(M4:M14) -> 0 | N15: =SUM(N4:N14) -> #DIV/0!
B18: ANALISE % Alocação da Carteira "Nasser Family" RENDA VARIAVEL(03/2024)
C19: % Renda Variavel Alocadas por Setor
B20: ='Planilha de Rentabilidade'!Z22+'Planilha de Rentabilidade'!W22 -> 0 | C20: =B20/$B$35 -> #DIV/0! | D20: Comodites_IRON ORE
B21: =+'Planilha de Rentabilidade'!O22 -> 0 | C21: =B21/$B$35 -> #DIV/0! | D21: SOJA
B22: ='Planilha de Rentabilidade'!AB22+'Planilha de Rentabilidade'!U22 -> 0 | C22: =B22/$B$35 -> #DIV/0! | D22: Electric Vehicle
B23: 0 | C23: =B23/$B$35 -> #DIV/0! | D23: Tec.NVIDIA
B24: 0 | C24: =B24/$B$35 -> #DIV/0! | D24: LITHIUM
B25: 0 | C25: =B25/$B$35 -> #DIV/0! | D25: industria BEBIDAS
B26: ='Planilha de Rentabilidade'!AH22 -> 0 | C26: =B26/$B$35 -> #DIV/0! | D26: CELULOSE
B27: ='Planilha de Rentabilidade'!AA22+'Planilha de Rentabilidade'!AC22 -> 0 | C27: =B27/$B$35 -> #DIV/0! | D27: Saude
B28: 0 | C28: =B28/$B$35 -> #DIV/0! | D28: Comodites_GOLD
B29: =+'Planilha de Rentabilidade'!Y22+'Planilha de Rentabilidade'!X22 -> 0 | C29: =B29/$B$35 -> #DIV/0! | D29: ASML
B30: 0 | C30: =B30/$B$35 -> #DIV/0! | D30: APPLE
B31: =+'Planilha de Rentabilidade'!N22 -> 0 | C31: =B31/$B$35 -> #DIV/0! | D31: INTEL
B32: 0 | C32: =B32/$B$35 -> #DIV/0! | D32: CARROCERIAS ONIBUS
C33: =SUM(C20:C32) -> #DIV/0!
B35: =SUM(B20:B34) -> 0 | C35: =B35/$B$35 -> #DIV/0!

Sheet % de Alocação da Carteira 05_25
B2: ANALISE % de Alocação da Carteira "Nasser Family"p/ Produto Financeiro (05/2023) | M2: ALOCAÇÃO % COMPACTA
E3: =SUM(E4:E14) -> #ERROR!
B4: CAIXA | D4: ='Planilha de Rentabilidade'!E38 -> 0 | E4: =D4/$D$15 -> #ERROR! | L4: IPCA + | M4: =SUM(D5:D7) -> 0 | N4: =M4/$M$15 -> #ERROR!
B5: TESOURO IPCA+2029 | D5: ='Planilha de Rentabilidade'!Q38 -> 0 | E5: =D5/$D$15 -> #ERROR! | N5: =M5/$M$15 -> #ERROR!
B6: DEBENTURE IPCA+7,60% | D6: ='Planilha de Rentabilidade'!P38 -> 0 | E6: =D6/$D$15 -> #ERROR! | M6: 0 | N6: =M6/$M$15 -> #ERROR!
B7: CRI CRA | D7: 0 | E7: =D7/$D$15 -> #ERROR! | L7: LCA | N7: =M7/$M$15 -> #ERROR!
B8: TESOURO SELIC + LFTS11 | D8: ='Planilha de Rentabilidade'!C38+'Planilha de Rentabilidade'!D38+'Planilha de Rentabilidade'!F38 -> 0 | E8: =D8/$D$15 -> #ERROR! | L8: RENDA FIXA | M8: =SUM(D8,D12,D13) -> 0 | N8: =M8/$M$15 -> #ERROR!
B9: MOEDAS | D9: ='Planilha de Rentabilidade'!L38 -> 0 | E9: =D9/$D$15 -> #ERROR! | L9: $$ | M9: =SUM(D9+D10) -> 0 | N9: =M9/$M$15 -> #ERROR!
B10: GOLD + $$$ | D10: ='Planilha de Rentabilidade'!M38 -> 0 | E10: =D10/$D$15 -> #ERROR! | N10: =M10/$M$15 -> #ERROR!
B11: LCA | D11: 0 | E11: =D11/$D$15 -> #ERROR! | N11: =M11/$M$15 -> #ERROR!
B12: FUNDO DI | D12: ='Planilha de Rentabilidade'!G38+'Planilha de Rentabilidade'!I38 -> 0 | E12: =D12/$D$15 -> #ERROR! | L12: CAIXA | M12: =D4 -> 0 | N12: =M12/$M$15 -> #ERROR!
B13: CDB DI | D13: ='Planilha de Rentabilidade'!H38+'Planilha de Rentabilidade'!J38+'Planilha de Rentabilidade'!K38+'Planilha de Rentabilidade'!S38+'Planilha de Rentabilidade'!V38 -> 0 | E13: =D13/$D$15 -> #ERROR! | N13: =M13/$M$15 -> #ERROR!
B14: RENDA VARIAVEL | D14: =B33 -> #ERROR! | E14: =D14/$D$15 -> #ERROR! | L14: Renda Variavel | M14: =D14 -> #ERROR! | N14: =M14/$M$15 -> #ERROR!
B15: Total da Carteira Nasser Family ==> | D15: =SUM(D4:D14) -> #ERROR! | E15: =SUM(E4:E14) -> #ERROR! | M15: =SUM(M4:M14) -> #ERROR! | N15: =SUM(N4:N14) -> #ERROR!
B18: ANALISE % Alocação da Carteira "Nasser Family" RENDA VARIAVEL(05/2023)
C19: % Renda Variavel Alocadas por Setor
B20: ='Planilha de Rentabilidade'!Z38 -> 0 | C20: =B20/$B$33 -> #ERROR! | D20: IRON ORE
B21: ='Planilha de Rentabilidade'!O38 -> 0 | C21: =B21/$B$33 -> #ERROR! | D21: SOJA
A22: CC | B22: ='Planilha de Rentabilidade'!U38+'Planilha de Rentabilidade'!AB38 -> 0 | C22: =B22/$B$33 -> #ERROR! | D22: Electric Vehicle
A23: FN | B23: =+'Planilha de Rentabilidade'!AG38 -> 0 | C23: =B23/$B$33 -> #ERROR! | D23: Tec.NVIDIA
A24: CM | B24: =+ -> #ERROR! | C24: =B24/$B$33 -> #ERROR! | D24: LITHIUM
A25: SD | B25: =+'Planilha de Rentabilidade'!AE38 -> 0 | C25: =B25/$B$33 -> #ERROR! | D25: FINANCEIRO
A26: GD | B26: 0 | C26: =B26/$B$33 -> #ERROR! | D26: CELULOSE
A27: EN | B27: ='Planilha de Rentabilidade'!AA38+'Planilha de Rentabilidade'!AC38 -> 0 | C27: =B27/$B$33 -> #ERROR! | D27: Saude
A28: VR | B28: 0 | C28: =B28/$B$33 -> #ERROR! | D28: Comodites_GOLD
A29: TC | B29: ='Planilha de Rentabilidade'!Y38+'Planilha de Rentabilidade'!X38 -> 0 | C29: =B29/$B$33 -> #ERROR! | D29: ASML
A30: SN | B30: ='Planilha de Rentabilidade'!T38 -> 0 | C30: =B30/$B$33 -> #ERROR! | D30: APPLE
B31: ='Planilha de Rentabilidade'!AH38+'Planilha de Rentabilidade'!N38 -> 0 | C31: =B31/$B$33 -> #ERROR! | D31: INTEL
B32: 0 | C32: =B32/$B$33 -> #ERROR! | D32: CARROCERIAS ONIBUS
B33: =SUM(B20:B32) -> #ERROR! | C33: =B33/$B$33 -> #ERROR!

Sheet % de Alocação da Carteira 06_25
B2: ANALISE % de Alocação da Carteira "Nasser Family"p/ Produto Financeiro (06/2023) | M2: ALOCAÇÃO % COMPACTA
E3: =+SUM(E4:E14) -> #DIV/0!
B4: CAIXA | D4: =+'Planilha de Rentabilidade'!E46 -> 0 | E4: =D4/$E$15 -> #DIV/0! | L4: IPCA + | M4: =+D5+D6 -> 0 | N4: =M4/$M$15 -> #DIV/0!
B5: TESOURO IPCA+2029 | D5: =+'Planilha de Rentabilidade'!Q46 -> 0 | E5: =D5/$E$15 -> #DIV/0! | N5: =M5/$M$15 -> #DIV/0!
B6: DEBENTURE IPCA+7,60% | D6: =+'Planilha de Rentabilidade'!P46 -> 0 | E6: =D6/$E$15 -> #DIV/0! | N6: =M6/$M$15 -> #DIV/0!
B7: CRI CRA | D7: 0 | E7: =D7/$E$15 -> #DIV/0! | L7: LCA | M7: 0 | N7: =M7/$M$15 -> #DIV/0!
B8: TESOURO SELIC + LFTS11 | D8: =+'Planilha de Rentabilidade'!C46+'Planilha de Rentabilidade'!D46+'Planilha de Rentabilidade'!F46 -> 0 | E8: =D8/$E$15 -> #DIV/0! | L8: RENDA FIXA | M8: =+D8+D12+D13 -> 0 | N8: =M8/$M$15 -> #DIV/0!
B9: MOEDAS | D9: =+'Planilha de Rentabilidade'!L46 -> 0 | E9: =D9/$E$15 -> #DIV/0! | L9: $$ | M9: =+D9+D10 -> 0 | N9: =M9/$M$15 -> #DIV/0!
B10: GOLD + $$$ | D10: =+'Planilha de Rentabilidade'!M46 -> 0 | E10: =D10/$E$15 -> #DIV/0! | M10: 0 | N10: =M10/$M$15 -> #DIV/0!
B11: LCA | D11: 0 | E11: =D11/$E$15 -> #DIV/0! | N11: =M11/$M$15 -> #DIV/0!
B12: FUNDO DI | D12: =+'Planilha de Rentabilidade'!G46+'Planilha de Rentabilidade'!I46 -> 0 | E12: =D12/$E$15 -> #DIV/0! | L12: CAIXA | M12: =+D4 -> 0 | N12: =M12/$M$15 -> #DIV/0!
B13: CDB DI | D13: =+'Planilha de Rentabilidade'!H46+'Planilha de Rentabilidade'!J46+'Planilha de Rentabilidade'!K46+'Planilha de Rentabilidade'!S46+'Planilha de Rentabilidade'!V46 -> 0 | E13: =D13/$E$15 -> #DIV/0! | N13: =M13/$M$15 -> #DIV/0!
B14: RENDA VARIAVEL | D14: =B33 -> 0 | E14: =D14/$E$15 -> #DIV/0! | L14: Renda Variavel | M14: =D14 -> 0 | N14: =M14/$M$15 -> #DIV/0!
C15: Total da Carteira Nasser Family ==> | E15: =SUM(D4:D14) -> 0 | M15: =SUM(M4:M14) -> 0 | N15: =SUM(N4:N14) -> #DIV/0!
B18: ANALISE % Alocação da Carteira "Nasser Family" RENDA VARIAVEL(06/2023)
C19: % Renda Variavel Alocadas por Setor
B20: =+'Planilha de Rentabilidade'!Z46 -> 0 | C20: =B20/$B$33 -> #DIV/0! | D20: IRON ORE
B21: =+'Planilha de Rentabilidade'!O46 -> 0 | C21: =B21/$B$33 -> #DIV/0! | D21: SOJA
B22: =+'Planilha de Rentabilidade'!U46+'Planilha de Rentabilidade'!AB46+'Planilha de Rentabilidade'!AF46 -> 0 | C22: =B22/$B$33 -> #DIV/0! | D22: Electric Vehicle
B23: 0 | C23: =B23/$B$33 -> #DIV/0! | D23: Tec.NVIDIA
B24: 0 | C24: =B24/$B$33 -> #DIV/0! | D24: LITHIUM
B25: ='Planilha de Rentabilidade'!AE46 -> 0 | C25: =B25/$B$33 -> #DIV/0! | D25: FINANCEIRO
B26: ='Planilha de Rentabilidade'!R46 -> 0 | C26: =B26/$B$33 -> #DIV/0! | D26: CELULOSE
B27: 0 | C27: =B27/$B$33 -> #DIV/0! | D27: Saude
B28: 0 | C28: =B28/$B$33 -> #DIV/0! | D28: Comodites_GOLD
B29: =+'Planilha de Rentabilidade'!X46+'Planilha de Rentabilidade'!Y46 -> 0 | C29: =B29/$B$33 -> #DIV/0! | D29: ASML
B30: =+'Planilha de Rentabilidade'!T46+'Planilha de Rentabilidade'!AG46 -> 0 | C30: =B30/$B$33 -> #DIV/0! | D30: APPLE
B31: =+'Planilha de Rentabilidade'!AH46+'Planilha de Rentabilidade'!N46 -> 0 | C31: =B31/$B$33 -> #DIV/0! | D31: INTEL
B32: 0 | C32: =B32/$B$33 -> #DIV/0! | D32: CARROCERIAS ONIBUS
B33: =SUM(B20:B32) -> 0 | C33: =B33/$B$33 -> #DIV/0!

Sheet % de Alocação da Carteira 07_25
B2: ANALISE % de Alocação da Carteira "Nasser Family"p/ Produto Financeiro (07/2023) | M2: ALOCAÇÃO % COMPACTA
E3: =+SUM(E4:E12) -> #DIV/0!
B4: CAIXA | D4: =+'Planilha de Rentabilidade'!E54 -> 0 | E4: =D4/$E$15 -> #DIV/0! | L4: IPCA + | M4: =+D5+D6 -> 0 | N4: =M4/$M$15 -> #DIV/0!
B5: TD IPCA+2029 | D5: =+'Planilha de Rentabilidade'!Q54 -> 0 | E5: =D5/$E$15 -> #DIV/0! | N5: =M5/$M$15 -> #DIV/0!
B6: DEBENTURE IPCA+7,60% | D6: =+'Planilha de Rentabilidade'!P54 -> 0 | E6: =D6/$E$15 -> #DIV/0! | N6: =M6/$M$15 -> #DIV/0!
B7: CRI CRA | D7: 0 | E7: =D7/$E$15 -> #DIV/0! | L7: FUNDOS | M7: =+D12 -> 0 | N7: =M7/$M$15 -> #DIV/0!
B8: TD SELIC+LFTS11 | D8: =+'Planilha de Rentabilidade'!C54+'Planilha de Rentabilidade'!D54+'Planilha de Rentabilidade'!F54 -> 0 | E8: =D8/$E$15 -> #DIV/0! | L8: RENDA FIXA | M8: =+D8+D13 -> 0 | N8: =M8/$M$15 -> #DIV/0!
B9: MOEDAS | D9: =+'Planilha de Rentabilidade'!L54 -> 0 | E9: =D9/$E$15 -> #DIV/0! | L9: $$ | M9: =+D9+D10 -> 0 | N9: =M9/$M$15 -> #DIV/0!
B10: GOLD + $$$ | D10: =+'Planilha de Rentabilidade'!M54 -> 0 | E10: =D10/$E$15 -> #DIV/0! | M10: 0 | N10: =M10/$M$15 -> #DIV/0!
B11: LCA | D11: 0 | E11: =D11/$E$15 -> #DIV/0! | N11: =M11/$M$15 -> #DIV/0!
B12: FUNDO DI | D12: =+'Planilha de Rentabilidade'!G54+'Planilha de Rentabilidade'!I54+'Planilha de Rentabilidade'!J54 -> 0 | E12: =D12/$E$15 -> #DIV/0! | L12: CAIXA | M12: =+D4 -> 0 | N12: =M12/$M$15 -> #DIV/0!
B13: CDB DI | D13: =+'Planilha de Rentabilidade'!H54+'Planilha de Rentabilidade'!K54+'Planilha de Rentabilidade'!S54+'Planilha de Rentabilidade'!V54 -> 0 | E13: =D13/$E$15 -> #DIV/0! | N13: =M13/$M$15 -> #DIV/0!
B14: RENDA VARIAVEL | D14: =B33 -> 0 | E14: =D14/$E$15 -> #DIV/0! | L14: Renda Variavel | M14: =D14 -> 0 | N14: =M14/$M$15 -> #DIV/0!
C15: Total da Carteira Nasser Family ==> | E15: =SUM(D4:D14) -> 0 | M15: =SUM(M4:M14) -> 0 | N15: =SUM(N4:N14) -> #DIV/0!
B18: ANALISE % Alocação da Carteira "Nasser Family" RENDA VARIAVEL(07/2023)
C19: % Renda Variavel Alocadas por Setor
B20: =+'Planilha de Rentabilidade'!Z54+'Planilha de Rentabilidade'!W54 -> 0 | C20: =B20/$B$33 -> #DIV/0! | D20: IRON ORE
B21: =+'Planilha de Rentabilidade'!O54 -> 0 | C21: =B21/$B$33 -> #DIV/0! | D21: SOJA
A22: CC | B22: =+'Planilha de Rentabilidade'!U54+'Planilha de Rentabilidade'!AB54+'Planilha de Rentabilidade'!AF54 -> 0 | C22: =B22/$B$33 -> #DIV/0! | D22: Electric Vehicle
A23: FN | B23: 0 | C23: =B23/$B$33 -> #DIV/0! | D23: Tec.NVIDIA
A24: CM | B24: 0 | C24: =B24/$B$33 -> #DIV/0! | D24: LITHIUM
A25: SD | B25: ='Planilha de Rentabilidade'!AE54+'Planilha de Rentabilidade'!AD54 -> 0 | C25: =B25/$B$33 -> #DIV/0! | D25: FINANCEIRO
A26: GD | B26: ='Planilha de Rentabilidade'!R54 -> 0 | C26: =B26/$B$33 -> #DIV/0! | D26: CELULOSE
A27: EN | B27: 0 | C27: =B27/$B$33 -> #DIV/0! | D27: Saude
A28: VR | B28: 0 | C28: =B28/$B$33 -> #DIV/0! | D28: Comodites_GOLD
A29: TC | B29: =+'Planilha de Rentabilidade'!X54+'Planilha de Rentabilidade'!Y54 -> 0 | C29: =B29/$B$33 -> #DIV/0! | D29: ASML
A30: SN | B30: =+'Planilha de Rentabilidade'!T54+'Planilha de Rentabilidade'!AG54 -> 0 | C30: =B30/$B$33 -> #DIV/0! | D30: APPLE
B31: =+'Planilha de Rentabilidade'!AH54+'Planilha de Rentabilidade'!N54 -> 0 | C31: =B31/$B$33 -> #DIV/0! | D31: INTEL
B32: 0 | C32: =B32/$B$33 -> #DIV/0! | D32: CARROCERIAS ONIBUS
B33: =SUM(B20:B32) -> 0 | C33: =B33/$B$33 -> #DIV/0!

Sheet % de Alocação da Carteira 08_25
B2: ANALISE % de Alocação da Carteira "Nasser Family"p/ Produto Financeiro (08/2023) | L2: 45505 | M2: ALOCAÇÃO % COMPACTA
E3: =+SUM(E4:E14) -> #DIV/0!
B4: CAIXA | D4: =+'Planilha de Rentabilidade'!E62 -> 0 | E4: =D4/$E$15 -> #DIV/0! | L4: IPCA + | M4: =+D5+D6 -> 0 | N4: =M4/$M$15 -> #DIV/0!
B5: TD IPCA+2029 | D5: =+'Planilha de Rentabilidade'!Q62 -> 0 | E5: =D5/$E$15 -> #DIV/0! | N5: =M5/$M$15 -> #DIV/0!
B6: DEBENTURE IPCA+7,60% | D6: =+'Planilha de Rentabilidade'!P62 -> 0 | E6: =D6/$E$15 -> #DIV/0! | N6: =M6/$M$15 -> #DIV/0!
B7: CRI CRA | D7: 0 | E7: =D7/$E$15 -> #DIV/0! | L7: FUNDOS | M7: =+D12 -> 0 | N7: =M7/$M$15 -> #DIV/0!
B8: TD SELIC+LFTS11 | D8: =+'Planilha de Rentabilidade'!C62+'Planilha de Rentabilidade'!D62+'Planilha de Rentabilidade'!F62 -> 0 | E8: =D8/$E$15 -> #DIV/0! | L8: RENDA FIXA | M8: =+D8+D13 -> 0 | N8: =M8/$M$15 -> #DIV/0!
B9: MOEDAS | D9: =+'Planilha de Rentabilidade'!L62 -> 0 | E9: =D9/$E$15 -> #DIV/0! | L9: $$ | M9: =+D9+D10 -> 0 | N9: =M9/$M$15 -> #DIV/0!
B10: GOLD + $$$ | D10: =+'Planilha de Rentabilidade'!M62 -> 0 | E10: =D10/$E$15 -> #DIV/0! | M10: 0 | N10: =M10/$M$15 -> #DIV/0!
B11: LCA | D11: 0 | E11: =D11/$E$15 -> #DIV/0! | N11: =M11/$M$15 -> #DIV/0!
B12: FUNDO DI | D12: =+'Planilha de Rentabilidade'!G62+'Planilha de Rentabilidade'!I62+'Planilha de Rentabilidade'!J62 -> 0 | E12: =D12/$E$15 -> #DIV/0! | L12: CAIXA | M12: =+D4 -> 0 | N12: =M12/$M$15 -> #DIV/0!
B13: CDB DI | D13: =+'Planilha de Rentabilidade'!H62+'Planilha de Rentabilidade'!K62+'Planilha de Rentabilidade'!S62+'Planilha de Rentabilidade'!V62 -> 0 | E13: =D13/$E$15 -> #DIV/0! | N13: =M13/$M$15 -> #DIV/0!
B14: RENDA VARIAVEL | D14: =B33 -> 0 | E14: =D14/$E$15 -> #DIV/0! | L14: Renda Variavel | M14: =D14 -> 0 | N14: =M14/$M$15 -> #DIV/0!
C15: Total da Carteira Nasser Family ==> | E15: =SUM(D4:D14) -> 0 | M15: =SUM(M4:M14) -> 0 | N15: =SUM(N4:N14) -> #DIV/0!
B18: ANALISE % Alocação da Carteira "Nasser Family"RENDA VARIAVEL(08/2023)
C19: % Renda Variavel Alocadas por Setor
B20: =+'Planilha de Rentabilidade'!Z62+'Planilha de Rentabilidade'!W62 -> 0 | C20: =B20/$B$33 -> #DIV/0! | D20: IRON ORE
B21: =+'Planilha de Rentabilidade'!O62 -> 0 | C21: =B21/$B$33 -> #DIV/0! | D21: SOJA
B22: =+'Planilha de Rentabilidade'!U62+'Planilha de Rentabilidade'!AF62 -> 0 | C22: =B22/$B$33 -> #DIV/0! | D22: Electric Vehicle
B23: 0 | C23: =B23/$B$33 -> #DIV/0! | D23: Tec.NVIDIA
B24: =+'Planilha de Rentabilidade'!AA62 -> 0 | C24: =B24/$B$33 -> #DIV/0! | D24: LITHIUM
B25: 0 | C25: =B25/$B$33 -> #DIV/0! | D25: FINANCEIRO
B26: 0 | C26: =B26/$B$33 -> #DIV/0! | D26: CELULOSE
B27: 0 | C27: =B27/$B$33 -> #DIV/0! | D27: Saude
B28: 0 | C28: =B28/$B$33 -> #DIV/0! | D28: Comodites_GOLD
B29: =+'Planilha de Rentabilidade'!X62+'Planilha de Rentabilidade'!Y62 -> 0 | C29: =B29/$B$33 -> #DIV/0! | D29: ASML
B30: =+'Planilha de Rentabilidade'!T62+'Planilha de Rentabilidade'!AG62 -> 0 | C30: =B30/$B$33 -> #DIV/0! | D30: APPLE
B31: =+'Planilha de Rentabilidade'!AH62+'Planilha de Rentabilidade'!N62 -> 0 | C31: =B31/$B$33 -> #DIV/0! | D31: INTEL
B32: ='Planilha de Rentabilidade'!AB62 -> 0 | C32: =B32/$B$33 -> #DIV/0! | D32: WEGE
B33: =SUM(B20:B32) -> 0 | C33: =B33/$B$33 -> #DIV/0!

Sheet % de Alocação da Carteira 09_25
B2: ANALISE % de Alocação da Carteira "Nasser Family"p/ Produto Financeiro (09/2023) | M2: ALOCAÇÃO % COMPACTA
E3: =+SUM(E4:E14) -> #DIV/0!
B4: CAIXA | D4: ='Planilha de Rentabilidade'!E70 -> 0 | E4: =D4/$E$15 -> #DIV/0! | L4: IPCA + | M4: =SUM(D5:D7) -> 0 | N4: =M4/$M$15 -> #DIV/0!
B5: TESOURO IPCA+2035 | D5: 0 | E5: =D5/$E$15 -> #DIV/0! | M5: 0 | N5: =M5/$M$15 -> #DIV/0!
B6: DEBENTURE | D6: ='Planilha de Rentabilidade'!P70 -> 0 | E6: =D6/$E$15 -> #DIV/0! | M6: 0 | N6: =M6/$M$15 -> #DIV/0!
B7: CRI CRA | D7: 0 | E7: =D7/$E$15 -> #DIV/0! | L7: LCA | M7: =+D11 -> 0 | N7: =M7/$M$15 -> #DIV/0!
B8: TESOURO SELIC + LFTS11 | D8: ='Planilha de Rentabilidade'!C70+'Planilha de Rentabilidade'!D70+'Planilha de Rentabilidade'!Q70+'Planilha de Rentabilidade'!F70 -> 0 | E8: =D8/$E$15 -> #DIV/0! | L8: RENDA FIXA | M8: =D8+D12+D13 -> 0 | N8: =M8/$M$15 -> #DIV/0!
B9: MOEDAS | D9: ='Planilha de Rentabilidade'!L70 -> 0 | E9: =D9/$E$15 -> #DIV/0! | L9: GOLD + $$ | M9: =+D10 -> 0 | N9: =M9/$M$15 -> #DIV/0!
B10: GOLD + $$$ | D10: ='Planilha de Rentabilidade'!M70 -> 0 | E10: =D10/$E$15 -> #DIV/0! | L10: MOEDAS | M10: =D9 -> 0 | N10: =M10/$M$15 -> #DIV/0!
B11: LCA | D11: 0 | E11: =D11/$E$15 -> #DIV/0! | N11: =M11/$M$15 -> #DIV/0!
B12: FUNDO DI | D12: ='Planilha de Rentabilidade'!G70+'Planilha de Rentabilidade'!I70+'Planilha de Rentabilidade'!J70 -> 0 | E12: =D12/$E$15 -> #DIV/0! | L12: CAIXA | M12: =+D4 -> 0 | N12: =M12/$M$15 -> #DIV/0!
B13: RENDA FIXA CDB DI | D13: ='Planilha de Rentabilidade'!K70 -> 0 | E13: =D13/$E$15 -> #DIV/0! | N13: =M13/$M$15 -> #DIV/0!
B14: RENDA VARIAVEL | D14: =B33 -> 0 | E14: =D14/$E$15 -> #DIV/0! | L14: R.V. | M14: =D14 -> 0 | N14: =M14/$M$15 -> #DIV/0!
C15: Total da Carteira Nasser Family ==> | E15: =SUM(D4:D14) -> 0 | M15: =SUM(M4:M14) -> 0 | N15: =SUM(N4:N14) -> #DIV/0!
B18: ANALISE % Alocação da Carteira "Nasser Family" RENDA VARIAVEL(09/2023)
C19: % Renda Variavel Alocadas por Setor
B20: ='Planilha de Rentabilidade'!Z70+'Planilha de Rentabilidade'!AD70+'Planilha de Rentabilidade'!W70 -> 0 | C20: =B20/$B$33 -> #DIV/0! | D20: IRON ORE
B21: 0 | C21: =B21/$B$33 -> #DIV/0! | D21: SOJA
B22: ='Planilha de Rentabilidade'!U70+'Planilha de Rentabilidade'!AF70 -> 0 | C22: =B22/$B$33 -> #DIV/0! | D22: Electric Vehicle
B23: ='Planilha de Rentabilidade'!F70 -> 0 | C23: =B23/$B$33 -> #DIV/0! | D23: Tec.NVIDIA
B24: ='Planilha de Rentabilidade'!AA70+'Planilha de Rentabilidade'!AE70 -> 0 | C24: =B24/$B$33 -> #DIV/0! | D24: LITHIUM
B25: 0 | C25: =B25/$B$33 -> #DIV/0! | D25: FINANCEIRO
B26: ='Planilha de Rentabilidade'!R70+'Planilha de Rentabilidade'!AC70 -> 0 | C26: =B26/$B$33 -> #DIV/0! | D26: CELULOSE
B27: 0 | C27: =B27/$B$33 -> #DIV/0! | D27: Saude
B28: 0 | C28: =B28/$B$33 -> #DIV/0! | D28: Comodites_GOLD
B29: ='Planilha de Rentabilidade'!X70+'Planilha de Rentabilidade'!Y70 -> 0 | C29: =B29/$B$33 -> #DIV/0! | D29: ASML
B30: ='Planilha de Rentabilidade'!AG70+'Planilha de Rentabilidade'!T70 -> 0 | C30: =B30/$B$33 -> #DIV/0! | D30: APPLE
B31: ='Planilha de Rentabilidade'!AH70+'Planilha de Rentabilidade'!N70 -> 0 | C31: =B31/$B$33 -> #DIV/0! | D31: INTEL
B32: ='Planilha de Rentabilidade'!AB70 -> 0 | C32: =B32/$B$33 -> #DIV/0! | D32: WEGE
B33: =SUM(B20:B32) -> 0 | C33: =B33/$B$33 -> #DIV/0!

Sheet % de Alocação da Carteira 10_25
B2: ANALISE % de Alocação da Carteira "Nasser Family"p/ Produto Financeiro (10/2025) | M2: ALOCAÇÃO % COMPACTA
E3: =+SUM(E4:E14) -> #DIV/0!
B4: CAIXA | D4: ='Planilha de Rentabilidade'!E78 -> 0 | E4: =D4/$E$15 -> #DIV/0! | L4: IPCA + | M4: =SUM(D5:D7) -> 0 | N4: =M4/$M$15 -> #DIV/0!
B5: TESOURO IPCA+2035 | D5: =+'Planilha de Rentabilidade'!Q78 -> 0 | E5: =D5/$E$15 -> #DIV/0! | M5: 0 | N5: =M5/$M$15 -> #DIV/0!
B6: DEBENTURE | D6: ='Planilha de Rentabilidade'!P78 -> 0 | E6: =D6/$E$15 -> #DIV/0! | M6: 0 | N6: =M6/$M$15 -> #DIV/0!
B7: CRI CRA | D7: 0 | E7: =D7/$E$15 -> #DIV/0! | L7: LCA | M7: =+D11 -> 0 | N7: =M7/$M$15 -> #DIV/0!
B8: TESOURO SELIC + LFTS11 | D8: ='Planilha de Rentabilidade'!C78+'Planilha de Rentabilidade'!D78+'Planilha de Rentabilidade'!F78 -> 0 | E8: =D8/$E$15 -> #DIV/0! | L8: RENDA FIXA | M8: =D8+D12+D13 -> 0 | N8: =M8/$M$15 -> #DIV/0!
B9: MOEDAS | D9: ='Planilha de Rentabilidade'!L78 -> 0 | E9: =D9/$E$15 -> #DIV/0! | L9: GOLD+$ | M9: =+D10 -> 0 | N9: =M9/$M$15 -> #DIV/0!
B10: GOLD+$ | D10: ='Planilha de Rentabilidade'!M78 -> 0 | E10: =D10/$E$15 -> #DIV/0! | L10: MOEDAS | M10: =D9 -> 0 | N10: =M10/$M$15 -> #DIV/0!
B11: LCA | D11: 0 | E11: =D11/$E$15 -> #DIV/0! | N11: =M11/$M$15 -> #DIV/0!
B12: FUNDO DI | D12: ='Planilha de Rentabilidade'!G78+'Planilha de Rentabilidade'!I78+'Planilha de Rentabilidade'!J78 -> 0 | E12: =D12/$E$15 -> #DIV/0! | L12: CAIXA | M12: =+D4 -> 0 | N12: =M12/$M$15 -> #DIV/0!
B13: CDB DI | D13: ='Planilha de Rentabilidade'!K78 -> 0 | E13: =D13/$E$15 -> #DIV/0! | N13: =M13/$M$15 -> #DIV/0!
B14: RENDA VARIAVEL | D14: =B33 -> 0 | E14: =D14/$E$15 -> #DIV/0! | L14: R. V. | M14: =D14 -> 0 | N14: =M14/$M$15 -> #DIV/0!
C15: Total da Carteira Nasser Family ==> | E15: =SUM(D4:D14) -> 0 | M15: =SUM(M4:M14) -> 0 | N15: =SUM(N4:N14) -> #DIV/0!
B18: ANALISE % Alocação da Carteira "Nasser Family" RENDA VARIAVEL(10/2023)
C19: % Renda Variavel Alocadas por Setor
B20: ='Planilha de Rentabilidade'!Z78++'Planilha de Rentabilidade'!W78 -> 0 | C20: =B20/$B$33 -> #DIV/0! | D20: IRON ORE
B21: 0 | C21: =B21/$B$33 -> #DIV/0! | D21: SOJA
B22: ='Planilha de Rentabilidade'!U78+'Planilha de Rentabilidade'!AF78 -> 0 | C22: =B22/$B$33 -> #DIV/0! | D22: Electric Vehicle
B23: ='Planilha de Rentabilidade'!V78 -> 0 | C23: =B23/$B$33 -> #DIV/0! | D23: CONSUMO
B24: ='Planilha de Rentabilidade'!AA78+'Planilha de Rentabilidade'!AE78 -> 0 | C24: =B24/$B$33 -> #DIV/0! | D24: LITHIUM
B25: =+'Planilha de Rentabilidade'!AD78+'Planilha de Rentabilidade'!AC78 -> 0 | C25: =B25/$B$33 -> #DIV/0! | D25: ENERGIA
B26: ='Planilha de Rentabilidade'!R70+'Planilha de Rentabilidade'!AC70 -> 0 | C26: =B26/$B$33 -> #DIV/0! | D26: CELULOSE
B27: 0 | C27: =B27/$B$33 -> #DIV/0! | D27: Saude
B28: =+'Planilha de Rentabilidade'!R78 -> 0 | C28: =B28/$B$33 -> #DIV/0! | D28: AURA_GOLD
B29: ='Planilha de Rentabilidade'!X78+'Planilha de Rentabilidade'!Y78 -> 0 | C29: =B29/$B$33 -> #DIV/0! | D29: ASML
B30: ='Planilha de Rentabilidade'!AG78+'Planilha de Rentabilidade'!T78 -> 0 | C30: =B30/$B$33 -> #DIV/0! | D30: APPLE
B31: ='Planilha de Rentabilidade'!AH78+'Planilha de Rentabilidade'!N78 -> 0 | C31: =B31/$B$33 -> #DIV/0! | D31: INTEL
B32: ='Planilha de Rentabilidade'!AB78 -> 0 | C32: =B32/$B$33 -> #DIV/0! | D32: WEGE
B33: =SUM(B20:B32) -> 0 | C33: =B33/$B$33 -> #DIV/0!

Sheet % de Alocação da Carteira 11_25
B2: ANALISE % de Alocação da Carteira "Nasser Family"p/ Produto Financeiro (11/2025) | M2: ALOCAÇÃO % COMPACTA
E3: =+SUM(E4:E14) -> #DIV/0!
B4: CAIXA | D4: ='Planilha de Rentabilidade'!E86 -> 0 | E4: =D4/$E$15 -> #DIV/0! | L4: IPCA + | M4: =SUM(D5:D7) -> 0 | N4: =M4/$M$15 -> #DIV/0!
B5: TESOURO IPCA+2035 | D5: =+'Planilha de Rentabilidade'!Q86 -> 0 | E5: =D5/$E$15 -> #DIV/0! | M5: 0 | N5: =M5/$M$15 -> #DIV/0!
B6: DEBENTURE | D6: =+'Planilha de Rentabilidade'!P86 -> 0 | E6: =D6/$E$15 -> #DIV/0! | M6: 0 | N6: =M6/$M$15 -> #DIV/0!
B7: CRI CRA | D7: 0 | E7: =D7/$E$15 -> #DIV/0! | L7: LCA | M7: =+D11 -> 0 | N7: =M7/$M$15 -> #DIV/0!
B8: TESOURO SELIC + LFTS11 | D8: ='Planilha de Rentabilidade'!C86+'Planilha de Rentabilidade'!D86+'Planilha de Rentabilidade'!S86+'Planilha de Rentabilidade'!F86 -> 0 | E8: =D8/$E$15 -> #DIV/0! | L8: RENDA FIXA | M8: =D8+D12+D13 -> 0 | N8: =M8/$M$15 -> #DIV/0!
B9: MOEDAS | D9: ='Planilha de Rentabilidade'!L86 -> 0 | E9: =D9/$E$15 -> #DIV/0! | L9: GOLD + $$ | M9: =+D10 -> 0 | N9: =M9/$M$15 -> #DIV/0!
B10: GOLD+$ | D10: ='Planilha de Rentabilidade'!M86 -> 0 | E10: =D10/$E$15 -> #DIV/0! | L10: MOEDAS | M10: =D9 -> 0 | N10: =M10/$M$15 -> #DIV/0!
B11: LCA | D11: =0 -> 0 | E11: =D11/$E$15 -> #DIV/0! | N11: =M11/$M$15 -> #DIV/0!
B12: FUNDO DI | D12: ='Planilha de Rentabilidade'!G86+'Planilha de Rentabilidade'!I86+'Planilha de Rentabilidade'!J86 -> 0 | E12: =D12/$E$15 -> #DIV/0! | L12: CAIXA | M12: =+D4 -> 0 | N12: =M12/$M$15 -> #DIV/0!
B13: CDB DI | D13: ='Planilha de Rentabilidade'!H86+'Planilha de Rentabilidade'!K86 -> 0 | E13: =D13/$E$15 -> #DIV/0! | N13: =M13/$M$15 -> #DIV/0!
B14: RENDA VARIAVEL | D14: =B33 -> 0 | E14: =D14/$E$15 -> #DIV/0! | L14: R.V. | M14: =D14 -> 0 | N14: =M14/$M$15 -> #DIV/0!
C15: Total da Carteira Nasser Family ==> | E15: =SUM(D4:D14) -> 0 | M15: =SUM(M4:M14) -> 0 | N15: =SUM(N4:N14) -> #DIV/0!
B18: ANALISE % Alocação da Carteira "Nasser Family" RENDA VARIAVEL(11/2025)
C19: % Renda Variavel Alocadas por Setor
B20: =+'Planilha de Rentabilidade'!Z86+'Planilha de Rentabilidade'!W86 -> 0 | C20: =B20/$B$33 -> #DIV/0! | D20: IRON ORE
B21: ='Planilha de Rentabilidade'!O86 -> 0 | C21: =B21/$B$33 -> #DIV/0! | D21: SOJA
B22: =+'Planilha de Rentabilidade'!AF86+'Planilha de Rentabilidade'!U86 -> 0 | C22: =B22/$B$33 -> #DIV/0! | D22: Electric Vehicle
B23: =+'Planilha de Rentabilidade'!V86+'Planilha de Rentabilidade'!AD86 -> 0 | C23: =B23/$B$33 -> #DIV/0! | D23: CONSUMO
B24: =+'Planilha de Rentabilidade'!AE86+'Planilha de Rentabilidade'!AA86 -> 0 | C24: =B24/$B$33 -> #DIV/0! | D24: LITHIUM
B25: 0 | C25: =B25/$B$33 -> #DIV/0! | D25: ENERGIA
B26: =0 -> 0 | C26: =B26/$B$33 -> #DIV/0! | D26: CELULOSE
B27: 0 | C27: =B27/$B$33 -> #DIV/0! | D27: Saude
B28: =+'Planilha de Rentabilidade'!R86 -> 0 | C28: =B28/$B$33 -> #DIV/0! | D28: AURA_GOLD
B29: =+'Planilha de Rentabilidade'!X86+'Planilha de Rentabilidade'!Y86+'Planilha de Rentabilidade'!AC86 -> 0 | C29: =B29/$B$33 -> #DIV/0! | D29: AMD
B30: ='Planilha de Rentabilidade'!T86+'Planilha de Rentabilidade'!AG86 -> 0 | C30: =B30/$B$33 -> #DIV/0! | D30: APPLE
B31: ='Planilha de Rentabilidade'!N86+'Planilha de Rentabilidade'!AH86 -> 0 | C31: =B31/$B$33 -> #DIV/0! | D31: INTEL
B32: =+'Planilha de Rentabilidade'!AB86 -> 0 | C32: =B32/$B$33 -> #DIV/0! | D32: WEGE
B33: =SUM(B20:B32) -> 0 | C33: =B33/$B$33 -> #DIV/0!

Sheet % de Alocação da Carteira 12_25
B2: ANALISE % de Alocação da Carteira "Nasser Family"p/ Produto Financeiro (12/2025) | M2: ALOCAÇÃO % COMPACTA
E3: =+SUM(E4:E14) -> #DIV/0!
B4: CAIXA | D4: =+'Planilha de Rentabilidade'!E94 -> 0 | E4: =D4/$E$15 -> #DIV/0! | L4: IPCA + | M4: =SUM(D5:D7) -> 0 | N4: =M4/$M$15 -> #DIV/0!
B5: TESOURO IPCA+2035 | D5: =+'Planilha de Rentabilidade'!Q94 -> 0 | E5: =D5/$E$15 -> #DIV/0! | M5: 0 | N5: =M5/$M$15 -> #DIV/0!
B6: DEBENTURE | D6: =+'Planilha de Rentabilidade'!P94 -> 0 | E6: =D6/$E$15 -> #DIV/0! | M6: 0 | N6: =M6/$M$15 -> #DIV/0!
B7: CRI CRA | D7: ='Planilha de Rentabilidade'!O94 -> 0 | E7: =D7/$E$15 -> #DIV/0! | L7: LCA | M7: =+D11 -> 0 | N7: =M7/$M$15 -> #DIV/0!
B8: TESOURO SELIC + LFTS11 | D8: ='Planilha de Rentabilidade'!C94+'Planilha de Rentabilidade'!D94+'Planilha de Rentabilidade'!S94+'Planilha de Rentabilidade'!F94 -> 0 | E8: =D8/$E$15 -> #DIV/0! | L8: RENDA FIXA | M8: =D8+D12+D13 -> 0 | N8: =M8/$M$15 -> #DIV/0!
B9: MOEDAS | D9: ='Planilha de Rentabilidade'!L94 -> 0 | E9: =D9/$E$15 -> #DIV/0! | L9: GOLD+$$ | M9: =+D10 -> 0 | N9: =M9/$M$15 -> #DIV/0!
B10: GOLD+$ | D10: ='Planilha de Rentabilidade'!M94 -> 0 | E10: =D10/$E$15 -> #DIV/0! | L10: MOEDAS | M10: =D9 -> 0 | N10: =M10/$M$15 -> #DIV/0!
B11: LCA | D11: =0 -> 0 | E11: =D11/$E$15 -> #DIV/0! | N11: =M11/$M$15 -> #DIV/0!
B12: FUNDO DI | D12: ='Planilha de Rentabilidade'!G94+'Planilha de Rentabilidade'!I94+'Planilha de Rentabilidade'!J94 -> 0 | E12: =D12/$E$15 -> #DIV/0! | L12: CAIXA | M12: =+D4 -> 0 | N12: =M12/$M$15 -> #DIV/0!
B13: CDB DI | D13: ='Planilha de Rentabilidade'!H94+'Planilha de Rentabilidade'!K94 -> 0 | E13: =D13/$E$15 -> #DIV/0! | N13: =M13/$M$15 -> #DIV/0!
B14: RENDA VARIAVEL | D14: =B33 -> 0 | E14: =D14/$E$15 -> #DIV/0! | L14: R.V. | M14: =D14 -> 0 | N14: =M14/$M$15 -> #DIV/0!
C15: Total da Carteira Nasser Family ==> | E15: =SUM(D4:D14) -> 0 | M15: =SUM(M4:M14) -> 0 | N15: =SUM(N4:N14) -> #DIV/0!
B18: ANALISE % Alocação da Carteira "Nasser Family" RENDA VARIAVEL(12/2025)
C19: % Renda Variavel Alocadas por Setor
B20: =+'Planilha de Rentabilidade'!Z94+'Planilha de Rentabilidade'!W94 -> 0 | C20: =B20/$B$33 -> #DIV/0! | D20: IRON ORE
B21: 0 | C21: =B21/$B$33 -> #DIV/0! | D21: SOJA
B22: =+'Planilha de Rentabilidade'!AF94+'Planilha de Rentabilidade'!U94 -> 0 | C22: =B22/$B$33 -> #DIV/0! | D22: Electric Vehicle
B23: =+'Planilha de Rentabilidade'!V94+'Planilha de Rentabilidade'!AD94 -> 0 | C23: =B23/$B$33 -> #DIV/0! | D23: CONSUMO
B24: =+'Planilha de Rentabilidade'!AE94 -> 0 | C24: =B24/$B$33 -> #DIV/0! | D24: LITHIUM
B25: 0 | C25: =B25/$B$33 -> #DIV/0! | D25: ENERGIA
B26: =0 -> 0 | C26: =B26/$B$33 -> #DIV/0! | D26: CELULOSE
B27: =+'Planilha de Rentabilidade'!AA94 -> 0 | C27: =B27/$B$33 -> #DIV/0! | D27: Saude
B28: =+'Planilha de Rentabilidade'!R94 -> 0 | C28: =B28/$B$33 -> #DIV/0! | D28: AURA_GOLD
B29: =+'Planilha de Rentabilidade'!X94+'Planilha de Rentabilidade'!Y946+'Planilha de Rentabilidade'!AC94 -> 0 | C29: =B29/$B$33 -> #DIV/0! | D29: AMD
B30: ='Planilha de Rentabilidade'!T94+'Planilha de Rentabilidade'!AG94 -> 0 | C30: =B30/$B$33 -> #DIV/0! | D30: APPLE
B31: ='Planilha de Rentabilidade'!N94+'Planilha de Rentabilidade'!AH94 -> 0 | C31: =B31/$B$33 -> #DIV/0! | D31: INTEL
B32: =+'Planilha de Rentabilidade'!AB94 -> 0 | C32: =B32/$B$33 -> #DIV/0! | D32: WEGE
B33: =SUM(B20:B32) -> 0 | C33: =B33/$B$33 -> #DIV/0!
